<?xml version="1.0" encoding="UTF-8"?><i><chatserver>chat.bilibili.com</chatserver><chatid>15675237</chatid><mission>0</mission><maxlimit>3000</maxlimit><source>k-v</source><d p="3.7539999485016,1,25,16777215,1491057902,0,71dc6b00,3164462366">来看晓之车</d>
<d p="1121.5699462891,1,25,16777215,1491059256,0,2496fc5b,3164583996">晓之车</d>
<d p="10.931200027466,1,25,16777215,1491060881,0,b668611f,3164708208">来听晓之车</d>
<d p="1124.5899658203,1,25,16777215,1491060965,0,b668611f,3164714650">晓之车</d>
<d p="1115.8299560547,5,25,16711680,1491061589,0,1453a1af,3164766468">来听晓之车</d>
<d p="1176.8900146484,1,25,16777215,1491064742,0,bbfb6749,3164982252">晓之车，真是怀念啊</d>
<d p="1115.4899902344,1,25,16777215,1491068832,0,14e4c564,3165165334">来听晓之车</d>
<d p="1353.5500488281,1,25,16777215,1491070627,0,a6f3da7c,3165219724">桌布~</d>
<d p="605.49102783203,5,25,16777215,1491071247,0,48d562c5,3165234734">↓其实我想知道芙蕾这是被睡了？</d>
<d p="1123.3499755859,5,25,16777215,1491071577,0,48d562c5,3165242084">神曲上线</d>
<d p="1141.8100585938,1,25,16777215,1491101282,0,ec0e511c,3165950900">最悲剧的喜欢的人是自己弟弟</d>
<d p="1260.4499511719,1,25,16777215,1491101329,0,ec0e511c,3165953462">喜喜</d>
<d p="0,1,25,16777215,1491104727,0,733cb640,3166154956">来听神曲</d>
<d p="1258.3800048828,1,25,16777215,1491104981,0,733cb640,3166170152">男女嘉宾牵手成功</d>
<d p="1159.6500244141,1,25,16777215,1491105381,0,2d611a2d,3166194588">晓之车~~</d>
<d p="1267.8800048828,1,25,16777215,1491105490,0,2d611a2d,3166201232">囍</d>
<d p="1275.7800292969,1,25,16777215,1491108660,0,1d80df1e,3166414398">yingx</d>
<d p="1277.4699707031,1,25,16777215,1491108599,0,1d80df1e,3166415370">印象中这幕最帅</d>
<d p="8.2189998626709,1,25,16777215,1491108899,0,aa5bf47d,3166429822">没人</d>
<d p="1277.3100585938,1,25,16777215,1491111716,0,484990c3,3166631498">火力压制</d>
<d p="1246.0999755859,5,25,16777215,1491113477,0,d1c41f47,3166753492">喔基佬</d>
<d p="72.556297302246,1,25,16777215,1491114541,0,04abf3fc,3166825214">三癞子果然是偷工减料得厉害，重复镜头用得飞起</d>
<d p="1249.2399902344,1,25,16777215,1491117020,0,e6e47753,3166989082">前面那个 哈哈哈哈哈</d>
<d p="1118.5300292969,5,25,15138834,1491122239,0,828956d8,3167357010">神曲上线</d>
<d p="1271.8699951172,1,25,16777215,1491123010,0,6feaeb8e,3167409994">喜</d>
<d p="1156.4000244141,1,25,16777215,1491128119,0,e90f0c6c,3167787504">晓之车</d>
<d p="1129.0899658203,1,25,16777215,1491128520,0,67b45c77,3167816944">啧啧啧</d>
<d p="1190.5200195312,1,25,16777215,1491128582,0,67b45c77,3167821634">狼式步枪</d>
<d p="1258.5999755859,5,25,16777215,1491138792,0,40695538,3168691994">男男嘉宾牵手成功</d>
<d p="531.15802001953,1,25,16776960,1491147235,0,b7009da1,3169514366">残存部队……</d>
<d p="607.42602539062,1,25,16776960,1491147338,0,b7009da1,3169524114">←被克队啊</d>
<d p="1055.1199951172,1,25,16777215,1491147772,0,9c81c412,3169563550">我记得这里重制版的晓之车插入没有原来的好</d>
<d p="1292.8199462891,1,25,16777215,1491147820,0,e90f0c6c,3169568020">挥之不去的画面</d>
<d p="1129.7099609375,1,25,16776960,1491147869,0,b7009da1,3169572516">晓之车</d>
<d p="1165.9100341797,1,25,16776960,1491147919,0,b7009da1,3169577048">基神完美继承了麻麻的美貌</d>
<d p="527.55700683594,1,25,16777215,1491153902,0,752dd761,3169986110">这字幕也太233了吧</d>
<d p="4.4210000038147,1,25,16777215,1491155208,0,772da9f3,3170039776">最经典的一集</d>
<d p="621.44000244141,1,25,16777215,1491158775,0,82de95e8,3170152132">队长原来是个受~要找钥匙</d>
<d p="1256.8800048828,1,25,16777215,1491174342,0,3e496ee4,3170351092">就算是开高达也要基给你看</d>
<d p="944.53399658203,1,25,16777215,1491183603,0,afa16510,3170673598">爸爸:我不听，我不听</d>
<d p="318.26599121094,1,25,16777215,1491190688,0,bbfb6749,3171142160">嗑药男其实很强，无非就是要嗑药，药断了就GG</d>
<d p="1087.4799804688,1,25,15138834,1491190930,0,a8b8bc35,3171159844">最感动的一幕要来了。</d>
<d p="1093.9599609375,1,25,15138834,1491190946,0,a8b8bc35,3171161002">最感动的片段</d>
<d p="1095.7600097656,1,25,15138834,1491190970,0,a8b8bc35,3171162872">最感动的片段要出现了。</d>
<d p="1119.8199462891,1,25,15138834,1491191000,0,a8b8bc35,3171165060">晓之车！</d>
<d p="18.159900665283,1,25,16777215,1491195779,0,8af11a47,3171536380">妥妥的来看天降自由！</d>
<d p="984.38800048828,1,25,16777215,1491197363,0,c172ebd9,3171671980">就这样被拐了</d>
<d p="1308.7299804688,1,25,15138834,1491202631,0,32b94782,3172098996">泪目</d>
<d p="1259.0600585938,1,25,16777215,1491203317,0,a2172c1c,3172152946">恭喜搞机成功</d>
<d p="1248.0200195312,5,25,16711680,1491203355,0,a2172c1c,3172155904">囍</d>
<d p="1258.3199462891,5,25,16711680,1491203382,0,a2172c1c,3172157992">恭喜男男嘉宾牵手成功</d>
<d p="1161.8699951172,1,25,16777215,1491205470,0,adb2ceb6,3172321902">等等，兄弟2333</d>
<d p="1073.0699462891,1,25,16777215,1491222787,0,f9db2fb7,3174157046">原版貌似这里就开始了</d>
<d p="1131.2800292969,1,25,16777215,1491224454,0,3f500b78,3174334656">真爱来了</d>
<d p="247.38000488281,1,25,16777215,1491227856,0,38dd6237,3174780838">b站正版啊啊   *٩(๑´∀`๑)ง*</d>
<d p="1.6210000514984,1,25,16777215,1491231091,0,7dfb655d,3175210132">来听晓之车</d>
<d p="1119.8800048828,1,25,16777215,1491231256,0,7dfb655d,3175219900">来听晓之车</d>
<d p="1389.25,1,25,16777215,1491237502,0,7e5e3135,3175900426">AK</d>
<d p="500.81399536133,5,25,16777215,1491238814,0,64bfed6a,3175993470">出拂晓，灭他们，对面又没有命运</d>
<d p="592.25402832031,5,25,16777215,1491238921,0,64bfed6a,3176000986">美人~</d>
<d p="42.581001281738,1,25,16777215,1491239557,0,17ebc847,3176039590">20170404</d>
<d p="955.708984375,1,25,16777215,1491245038,0,9006c431,3176281102">爸爸</d>
<d p="984.14099121094,1,25,16777215,1491245066,0,9006c431,3176281876">爸爸：里面藏了一台，不过要第二季开始</d>
<d p="1248.9399414062,1,25,16777215,1491245332,0,9006c431,3176289032">经典</d>
<d p="9.1040000915527,1,25,16777215,1491268017,0,6050a3ab,3176886856">晓之车啊</d>
<d p="1233.6899414062,1,25,16777215,1491268057,0,6050a3ab,3176888896">激情握手</d>
<d p="1255.3100585938,1,25,16777215,1491268079,0,6050a3ab,3176889984">哦基佬笑尿</d>
<d p="181.67300415039,1,25,16777215,1491269240,0,11985b93,3176975062">高达系列真的有些不科学</d>
<d p="613.50701904297,1,25,16707842,1491269653,0,11985b93,3177066262">哈哈</d>
<d p="1115.5999755859,1,25,16777215,1491269816,0,1bbdb222,3177076478">晓之车！</d>
<d p="1119.7800292969,1,25,16777215,1491272737,0,01ef07ed,3177349316">居然在这种地方卡主了</d>
<d p="254.54899597168,1,25,16777215,1491273186,0,1bfb042f,3177389506">思想钢印</d>
<d p="1278.8499755859,1,25,16777215,1491278855,0,38287838,3178041938">yoooooo</d>
<d p="1223.6099853516,1,25,16777215,1491280285,0,6336981f,3178227622">QAQ</d>
<d p="1298.0999755859,1,25,16777215,1491281075,0,2086a6f0,3178299656">真够MAN!</d>
<d p="750.18103027344,1,25,16777215,1491286418,0,0fdaba95,3178883052">毕竟核能源这续航能力 杠杠的</d>
<d p="1144.9000244141,1,25,16777215,1491287943,0,ff31e267,3179104016">神曲~！</d>
<d p="1334.5899658203,1,25,16777215,1491292361,0,80527e4d,3179483034">奥布雄狮~~~</d>
<d p="783.95300292969,1,25,16777215,1491292833,0,efc1dc87,3179522860">其实不会，阿斯兰和基拉现在都没爆种</d>
<d p="783.95300292969,1,25,16777215,1491292854,0,efc1dc87,3179524700">况且不是有拂晓吗</d>
<d p="690.64801025391,1,25,16777215,1491293519,0,05ee7742,3179581026">快溜快溜</d>
<d p="1353.4000244141,1,25,16777215,1491295169,0,c87b1170,3179723584">这个好美。以前ed没看到这</d>
<d p="585.91400146484,1,25,16777215,1491296588,0,24d51713,3179973882">结果把自己家的信息也收集进去了233</d>
<d p="687.88000488281,1,25,16777215,1491296690,0,24d51713,3179982388">每次看他们内讧真是搞笑</d>
<d p="709.07800292969,1,25,16777215,1491300387,0,a2919af5,3180399134">回去找小黄</d>
<d p="1347.3199462891,1,25,16777215,1491306789,0,01fb03ed,3181099550">作诗？？ 梶浦由记？ 官方6</d>
<d p="1343.9499511719,1,25,16777215,1491307415,0,a1885756,3181154214">这男人</d>
<d p="1243.1400146484,5,25,16777215,1491312879,0,32f9ab5b,3181708404">名场面要来了</d>
<d p="235.28399658203,1,25,16777215,1491313343,0,9dc8ef2d,3181750532">为了小哥找到人生目标了？</d>
<d p="1265.5699462891,1,25,16777215,1491314322,0,9dc8ef2d,3181927626">吻他</d>
<d p="1281.5600585938,1,25,16777215,1491318401,0,04f142d3,3182317636">后话：因载重失衡，此次升空严重偏离预定位置。</d>
<d p="243.47700500488,1,25,16777215,1491323190,0,ff908481,3182676022">名言</d>
<d p="1099.4899902344,1,25,16777215,1491323749,0,ff908481,3182709126">一会基友牵手扒火车</d>
<d p="1285.1400146484,1,25,16777215,1491323921,0,ff908481,3182718670">基情组合技</d>
<d p="1106.9200439453,1,25,16777215,1491325463,0,ea00ee80,3182789460">一直不明白这是什么原理</d>
<d p="457.79501342773,1,25,16777215,1491350428,0,9823d574,3183144410">双男主光环开启????！！！</d>
<d p="678.4169921875,1,25,16777215,1491392263,0,79449104,3185919040">这三个太6了，能和两主角打这么久</d>
<d p="2.9100000858307,1,25,16777215,1491392336,0,9e1cb5bb,3185923980">特意跳过来听歌</d>
<d p="1100.8599853516,1,25,16777215,1491392811,0,9e1cb5bb,3185955352">最经典的来了</d>
<d p="279.72100830078,1,25,16777215,1491394137,0,75d7b070,3186047752">才发现吗</d>
<d p="619.53698730469,1,25,16776960,1491396395,0,33017728,3186329192">我怎么黄了</d>
<d p="1285.8800048828,1,25,16777215,1491397631,0,75d7b070,3186423028">三小强火力真准</d>
<d p="1341.5600585938,1,25,16777215,1491397700,0,75d7b070,3186428296">真能挺</d>
<d p="1325.4200439453,1,25,16777215,1491398971,0,a3ef5ef2,3186526894">这个重制版又重置过了吧,我记得刚出来的时候是remix的晓之车</d>
<d p="446.91299438477,1,25,16777215,1491400259,0,00fbfd8b,3186631314">基友（夫妻）混合双打开始了</d>
<d p="1379.6199951172,1,25,16777215,1491400458,0,e753a7aa,3186647740">橙色头发是海涅吗</d>
<d p="1268.3399658203,1,25,16777215,1491400473,0,00fbfd8b,3186648962">恭喜牵手成功</d>
<d p="1305.7399902344,1,25,16777215,1491400510,0,00fbfd8b,3186652270">奥布再见了</d>
<d p="53.796001434326,1,25,16777215,1491401434,0,7e9aed71,3186866608">20170405</d>
<d p="776.39202880859,1,25,16777215,1491403543,0,0099e858,3187115834">晓之车来拉~~~~~~~~~~~~~~~~~~~~~~~~~</d>
<d p="423.23599243164,1,25,16777215,1491403591,0,ad4b872c,3187119714">回旋镖有动力？</d>
<d p="460.95401000977,1,25,16777215,1491403647,0,ad4b872c,3187124384">有名字的杂兵和有台词的杂兵</d>
<d p="504.3030090332,1,25,16777215,1491403717,0,ad4b872c,3187131164">拂晓幸亏没在73年给她否则早没了</d>
<d p="604.99597167969,1,25,16777215,1491403845,0,ad4b872c,3187141384">克队666666</d>
<d p="610.88397216797,1,25,16777215,1491403867,0,ad4b872c,3187143272">当然了还可以用其他的射</d>
<d p="995.08801269531,1,25,16777215,1491404286,0,ad4b872c,3187179554">你们说这帮人要是知道里面私藏了一台性能强到不行的拂晓会怎么想</d>
<d p="1104.4599609375,1,25,16777215,1491404420,0,ad4b872c,3187190286">基友联手的经典画面</d>
<d p="1298.5100097656,1,25,16777215,1491404654,0,ad4b872c,3187209636">背后惊现    温丞相…………</d>
<d p="1388.7099609375,1,25,16777215,1491404762,0,ad4b872c,3187218374">海涅和阿斯兰原本不认识</d>
<d p="737.81201171875,1,25,16777215,1491408412,0,df3227dd,3187483414">竟然喘气了。。</d>
<d p="1253.0200195312,1,25,16777215,1491444551,0,fe211aa9,3188302696">被打下来就好玩了</d>
<d p="548.28497314453,1,25,16777215,1491447003,0,70bf2dbd,3188442110">胡志密？？？？？</d>
<d p="1260.6700439453,1,25,16777215,1491461535,0,a4ed9709,3189286106">YOOOOOOOOOOOOOOOOOOOOOO</d>
<d p="1338.4499511719,1,25,16777215,1491461617,0,a4ed9709,3189288672">胡志明</d>
<d p="201.01899719238,1,25,16777215,1491471758,0,c824d5e5,3189801468">前面说不科学的，牛顿的棺材板见过吗</d>
<d p="1134.9000244141,1,25,15138834,1491478623,0,bf54d92d,3190228012">晓之车</d>
<d p="1274.6999511719,1,25,15138834,1491478778,0,bf54d92d,3190238180">合体技 来了</d>
<d p="1125.6800537109,1,25,16777215,1491479778,0,d312d97a,3190305388">就是来听歌的</d>
<d p="733.78497314453,1,25,16777215,1491481516,0,f04e3b08,3190431498">都没爆种....</d>
<d p="1251.1400146484,1,25,16777215,1491481759,0,3ccaef53,3190449176">两位男嘉宾牵手成功</d>
<d p="1271.9000244141,1,25,16777215,1491481786,0,3ccaef53,3190451062">管子有点多啊</d>
<d p="427.26800537109,1,25,16777215,1491487661,0,3f8b8fc0,3190965620">有的 可回收的</d>
<d p="712.98901367188,1,25,16777215,1491487982,0,3f8b8fc0,3190992084">我才发现还没爆种</d>
<d p="1290.0600585938,1,25,16777215,1491488633,0,3f8b8fc0,3191047388">不是，是因为不能打坏轨道，所以才打不中</d>
<d p="1364.5100097656,1,25,16777215,1491488645,0,3f8b8fc0,3191055982">这是seedd的形象吧</d>
<d p="1214.5400390625,1,25,15138834,1491490064,0,b145fe7b,3191172146">速度的话自由比较快</d>
<d p="1259.3499755859,1,25,15138834,1491490118,0,b145fe7b,3191176956">齐射！</d>
<d p="41.556999206543,5,25,16707842,1491491296,0,ad288a0c,3191281298">这是想多了</d>
<d p="378.01599121094,5,25,16777215,1491495950,0,10014718,3191617264">基拉:不能让我安安静静的削个人棍吗</d>
<d p="1180.6700439453,1,25,16707842,1491499637,0,8eb7a34e,3191768454">奥布之魂</d>
<d p="1305.5899658203,1,25,16707842,1491499783,0,8eb7a34e,3191772668">奥布之狮</d>
<d p="78.939002990723,1,25,16777215,1491520734,0,c0018482,3192025352">23333</d>
<d p="352.12100219727,1,25,16777215,1491536393,0,1aceb80f,3192528968">都闪开，基神开大了</d>
<d p="353.66400146484,1,25,16777215,1491542123,0,d6861171,3193044932">先清兵，加点气力</d>
<d p="1298.5100097656,1,25,16777215,1491559297,0,4b662a15,3194116294">不能打坏宇宙跑道</d>
<d p="1375.7600097656,1,25,16777215,1491559472,0,4b662a15,3194122430">基友变姐夫</d>
<d p="1337.5300292969,1,25,16777215,1491562307,0,d6b3443d,3194350702">一路走好</d>
<d p="634.17797851562,1,25,16777215,1491562646,0,e944c87a,3194370978">战斗把枪 。。。。嗞嗞</d>
<d p="625.78601074219,1,25,16777215,1491565037,0,4e994b22,3194568472">核能机体厉害了</d>
<d p="1167.4599609375,1,25,16777215,1491565163,0,e8869b5a,3194579274">我喜欢的人竟然是我哥哥</d>
<d p="1183.9899902344,1,25,16777215,1491565179,0,e8869b5a,3194585086">爸爸要gg了吗</d>
<d p="1256.7600097656,1,25,16777215,1491565252,0,e8869b5a,3194591342">哦基佬笑死我了</d>
<d p="1281.1300048828,1,25,16777215,1491565276,0,e8869b5a,3194593430">默契无双</d>
<d p="1321.5899658203,1,25,16777215,1491565316,0,e8869b5a,3194596872">说炸就炸</d>
<d p="1113.4499511719,1,25,255,1491565502,0,4e994b22,3194612538">神曲上线啊</d>
<d p="1266.2600097656,1,25,16777215,1491568469,0,19758c40,3194873468">理科要爆炸了</d>
<d p="1297.9899902344,1,25,16707842,1491572773,0,5d0fc0e0,3195285186">奥布和世界都不会任他们摆布的！</d>
<d p="512,1,25,16777215,1491573428,0,1b8cc266,3195354166">CE71还是实弹系为主，拂晓上不是送死</d>
<d p="1164.5899658203,1,25,16777215,1491576444,0,3a42389c,3195782068">小时候在东西动漫社看到的片段</d>
<d p="1056.0300292969,1,25,16777215,1491576843,0,c210cd1d,3195821948">来听晓之车的。。。</d>
<d p="190.16400146484,1,25,16777215,1491580305,0,fafd107a,3196166000">高达的存在本身就不科学</d>
<d p="277.4700012207,1,25,16777215,1491581455,0,619cf1f7,3196270690">迪亚哥:mmp你才发现我！</d>
<d p="1.6360000371933,1,25,16777215,1491581738,0,777a0d61,3196292196">听歌</d>
<d p="418.72799682617,1,25,16777215,1491581900,0,777a0d61,3196304104">justice!</d>
<d p="1117.5999755859,1,25,16777215,1491582143,0,777a0d61,3196321268">我想哭了...</d>
<d p="1406.1700439453,1,25,16777215,1491595535,0,3274957c,3196775752">食物链顶端的夫妇→_→</d>
<d p="614.65301513672,1,25,16777215,1491632314,0,77339bd7,3198364268">并没有啊</d>
<d p="756.83099365234,1,25,16777215,1491632478,0,77339bd7,3198375938">理论上半永久驱动的</d>
<d p="1271.3900146484,1,25,16777215,1491632864,0,a577654a,3198403144">共计8管炮（正义2+自由4+光束步枪2）</d>
<d p="420.7200012207,1,25,16777215,1491635927,0,0ec7f790,3198613692">为什么刚才有黄色的射线</d>
<d p="460.79901123047,1,25,16777215,1491651869,0,b8a3fabd,3199902336">这杂兵的眼睛跟爆种了似的</d>
<d p="25.834999084473,1,25,16777215,1491653026,0,26ab0437,3200010652">只为晓之车</d>
<d p="189.08799743652,1,25,16777215,1491655394,0,f423cf34,3200241950">前面的醒醒，这只是动漫</d>
<d p="206.90699768066,1,25,16777215,1491655439,0,f423cf34,3200246312">前面的牛顿的棺材板的，人家棺材版很忙的</d>
<d p="509.51901245117,1,25,16777215,1491655743,0,f423cf34,3200275958">23333</d>
<d p="609.04998779297,1,25,16777215,1491655844,0,f423cf34,3200285826">？？？</d>
<d p="717.43402099609,1,25,16777215,1491655989,0,f423cf34,3200300070">233333</d>
<d p="1007.5900268555,1,25,16777215,1491656280,0,f423cf34,3200328316">又来23333</d>
<d p="1273.6700439453,1,25,16777215,1491656551,0,f423cf34,3200354734">卧槽23333333333</d>
<d p="1079.5300292969,1,25,16777215,1491659938,0,3b7cac1f,3200716422">是飞走那里开始的吧</d>
<d p="1115.2299804688,1,25,16777215,1491659988,0,3b7cac1f,3200721660">神曲上线</d>
<d p="1233.4599609375,1,25,16777215,1491660131,0,3b7cac1f,3200736328">开了必闪了</d>
<d p="1381.6400146484,1,25,16777215,1491660332,0,3b7cac1f,3200757454">那个是海捏么？</d>
<d p="1297.3599853516,1,25,16777215,1491668542,0,50ef779c,3201595504">强紫一台15门炮</d>
<d p="1384.1600341797,1,25,16777215,1491677207,0,c396b3fc,3202091734">拉斯提吧第一集炮灰的红衣</d>
<d p="405.63400268555,1,25,16777215,1491677346,0,7a3e3579,3202095682">第一次知道盾牌小孔可以打枪</d>
<d p="1165.8100585938,1,25,16777215,1491678147,0,7a3e3579,3202116764">段王爷？</d>
<d p="1262.2199707031,1,25,16777215,1491678250,0,7a3e3579,3202119270">开高达也能搞基</d>
<d p="1397.2299804688,1,25,16777215,1491678433,0,7a3e3579,3202123762">全剧终</d>
<d p="731.23297119141,1,25,16777215,1491693802,0,f4cb2b10,3202326334">这两位的光束剑都是有牌子的，游戏里叫天蝎座</d>
<d p="1309.2299804688,1,25,16777215,1491697545,0,f43d920e,3202421816">settle！</d>
<d p="357.8330078125,1,25,16777215,1491698627,0,e52b270e,3202461878">每次都觉得基拉头盔上出现的的蝴蝶结帅爆了，因为大招就要来了</d>
<d p="1242.8499755859,1,25,16777215,1491705345,0,841a8de7,3202841050">为什么红色不是3倍速。</d>
<d p="1315.0600585938,1,25,16777215,1491712337,0,2caca485,3203394484">再见</d>
<d p="1343.0600585938,1,25,16777215,1491712367,0,2caca485,3203397138">好人一路走好</d>
<d p="1360.5300292969,1,25,16777215,1491712384,0,2caca485,3203398664">女神</d>
<d p="1335.4499511719,1,25,16777215,1491716468,0,bc1357b3,3203791900">奥布这批领导人真好</d>
<d p="1321.1899414062,1,25,16777215,1491718712,0,2b2f6c4b,3203993400">走好</d>
<d p="1127.6300048828,1,25,16777215,1491723397,0,a0bf5329,3204385106">神曲上线</d>
<d p="1252.0200195312,1,25,16777215,1491723458,0,581511b0,3204389738">男男嘉宾牵手成功 </d>
<d p="1301.1300048828,1,25,16777215,1491723520,0,581511b0,3204394850">磁力种子飞走了</d>
<d p="1235.5899658203,1,25,16777215,1491723558,0,a0bf5329,3204397796">男嘉宾和男嘉宾牵手成功</d>
<d p="1378.4399414062,1,25,16750848,1491723744,0,a0bf5329,3204415500">                          海涅↓</d>
<d p="992.90502929688,1,25,16777215,1491728634,0,536f1ef3,3204816110">阿斯拉 ; 基拉你个诱拐犯 ~</d>
<d p="456.30999755859,1,25,16777215,1491738722,0,2ea9edec,3205626642">说起来这时候罗应该在奥布的另一边的战场吧</d>
<d p="684.41802978516,1,25,16777215,1491738988,0,2ea9edec,3205648282">三小强现在都是独自作战啊  双主角还是互相合作  </d>
<d p="555.14001464844,1,25,16777215,1491740313,0,4a27d0e3,3205758134">字幕能上点心吗……</d>
<d p="772.00402832031,1,25,16777215,1491750910,0,86525f0b,3206711552">送走灾星，受不了了2333</d>
<d p="1399.6899414062,1,25,16777215,1491751362,0,86525f0b,3206750562">半透明的情趣裙子？好污</d>
<d p="302.35000610352,1,25,16777215,1491752141,0,f6960f83,3206814992">先说的“他”后面才加的“们”</d>
<d p="828.93701171875,1,25,6737151,1491760650,0,7116053f,3207239056">翻译应该是“要想知道另一个未来的话”</d>
<d p="1053.3900146484,1,25,6737151,1491760956,0,7116053f,3207246922">不过这时候穆叔竟然不出击233</d>
<d p="1065.6099853516,1,25,6737151,1491761000,0,7116053f,3207247968">舰长：不行，使用阳电子炮会破坏地球环境 2333</d>
<d p="1275.1199951172,1,25,6737151,1491761384,0,7116053f,3207256860">就六炮好么，说拿枪的那个，你右手不抓船了？</d>
<d p="1401.0500488281,1,25,6737151,1491761814,0,7116053f,3207266362">拉克丝腿这么细有点可怕看着。。</d>
<d p="704.87799072266,1,25,16777215,1491793263,0,fceec710,3207731474">溜了溜了</d>
<d p="1376.9200439453,1,25,16777215,1491793983,0,32a5351d,3207749882">结尾画面重置了</d>
<d p="14.699999809265,1,25,16777215,1491794968,0,b9a238d4,3207779632">有人</d>
<d p="370.16198730469,1,25,16777215,1491801592,0,b1e3017d,3208200468">这火力压制</d>
<d p="1249.3100585938,1,25,16777215,1491801660,0,79474f9f,3208204498">原本很伤感，看到这个不厚道的笑了</d>
<d p="302.02801513672,1,25,16777215,1491804230,0,af45ca28,3208327264">反水了</d>
<d p="564.73199462891,1,25,16777215,1491804497,0,af45ca28,3208339254">没有点心 滚</d>
<d p="1224.8499755859,1,25,16777215,1491811308,0,728d497d,3208568840">速度是骑飞板的正义更快，不骑和自由持平</d>
<d p="847.53399658203,1,25,16777215,1491824164,0,fdcaeb19,3209284808">传火了</d>
<d p="616.72399902344,1,25,16777215,1491827664,0,e91554e3,3209526778">你捡到的怕是把锁吧</d>
<d p="665.89001464844,1,25,16777215,1491827747,0,e91554e3,3209532872">药效够长了，能量又不够了</d>
<d p="1243.5100097656,1,25,16777215,1491831266,0,9f77c334,3209807530">突然断了就尴尬啦</d>
<d p="1006.1500244141,1,25,16777215,1491832392,0,dd46e615,3209900592">拂晓是谁开的？</d>
<d p="1019.4699707031,1,25,16777215,1491832405,0,dd46e615,3209902710">拂晓是谁的啊？</d>
<d p="224.25,1,25,16777215,1491833845,0,4350e458,3210028070">前面牛顿棺材板忙的，牛顿才是真的忙</d>
<d p="1011.3699951172,1,25,16777215,1491839604,0,1ff956bf,3210517564">拂晓是卡嘉丽的专用机体</d>
<d p="1193.0799560547,1,25,16777215,1491839856,0,1ff956bf,3210536642">大天使到哪，哪里就爆炸2333</d>
<d p="846.28302001953,1,25,16777215,1491840735,0,45f13bd7,3210593526">传火吧</d>
<d p="1023,1,25,16711791,1491842886,0,7ab57a66,3210702726">主要是穆叔开</d>
<d p="751.92901611328,1,25,16777215,1491870652,0,e178fde1,3211088944">龙马  ？？？</d>
<d p="60.080001831055,1,25,16777215,1491873081,0,b8d1dcce,3211133722">20170411</d>
<d p="779.92401123047,1,25,16777215,1491879574,0,96f73333,3211302312">哈哈，大灾星号你快走吧，快被你坑死了</d>
<d p="230.1840057373,1,25,16777215,1491886264,0,3b6ed892,3211675604">前面说牛顿棺材板的  你知道棺材店老板很忙的好吗</d>
<d p="856.11901855469,1,25,16777215,1491892168,0,70395b2e,3211972096">喵喵喵？</d>
<d p="1000.1199951172,1,25,15138834,1491910347,0,0c1b9314,3212886840">就算知道有拂晓也没用，战争不会因为一台机体停止</d>
<d p="312.65899658203,1,25,16777215,1491910736,0,1a74c516,3212912232">还好吧，虽然帮助了长腿，但是打的还是地球军</d>
<d p="1363.5,1,25,15138834,1491910884,0,0c1b9314,3212921432">新画面，三周目值得了</d>
<d p="93.138000488281,1,25,16777215,1491919118,0,d08abe28,3213526816">20170411</d>
<d p="1151.8000488281,1,25,16777215,1491923686,0,d1264f7d,3214006092">要成长了呀</d>
<d p="1269.2600097656,1,25,16777215,1491923803,0,d1264f7d,3214015014">签收成功</d>
<d p="1373.5699462891,1,25,16777215,1491923907,0,d1264f7d,3214022830">超喜欢拉克丝</d>
<d p="857.87799072266,1,25,16777215,1491928259,0,9a1d94c3,3214301916">要认亲了</d>
<d p="1154.8299560547,1,25,16777215,1491928564,0,9a1d94c3,3214315978">亲人</d>
<d p="1383.3299560547,1,25,16777215,1491928811,0,9a1d94c3,3214327062">那是拉斯提...</d>
<d p="733.66101074219,1,25,16777215,1491933058,0,3f289773,3214466208">这三人确实很强，压得决斗高达不能翻身啊，</d>
<d p="1223.8900146484,1,25,16777215,1491933488,0,3f289773,3214475932">错了，论速度的话。正义比较快。</d>
<d p="771.01800537109,1,25,16777215,1491966332,0,b7d8d8cb,3215058280">胡子密大人????????????????</d>
<d p="7.0009999275208,1,25,16777215,1491979058,0,3248325f,3215657370">三癞子</d>
<d p="1142.25,1,25,16777215,1491979181,0,3248325f,3215662214">这蛋疼的名字分分钟出戏</d>
<d p="753.02398681641,1,25,16777215,1491981048,0,b07e3c42,3215723238">阿斯绿:基拉你抢我妞就算了，还抢我吹泡泡的玩具(งᵒ̌皿ᵒ̌)ง⁼³₌₃</d>
<d p="571.88800048828,1,25,16777215,1491991165,0,34e66a8f,3216125650">看看隔壁强殖装甲错别字要上天，后来直接没字幕那才是心塞哭</d>
<d p="1099.3399658203,1,25,16777215,1492001422,0,1e612b41,3216783232">当时看得哭死我了</d>
<d p="284.07800292969,1,25,16777215,1492007065,0,1f4a076c,3217211854">心疼233333</d>
<d p="1114.8699951172,1,25,16777215,1492011405,0,84d6d988,3217544696">美的不行</d>
<d p="1289.1999511719,1,25,16777215,1492011574,0,84d6d988,3217562596">我自己都不记的是第几便遍看了????????</d>
<d p="1324.4699707031,1,25,16777215,1492017565,0,7cfa78ac,3217842036">只是炸了曙光厂而已</d>
<d p="453.59399414062,1,25,16777215,1492021505,0,77cdb94c,3217930464">爆各种就解决的事情</d>
<d p="1189.4000244141,1,25,16777215,1492035672,0,b9fab286,3218055258">10年前和10年后如今看到这一幕，还是不禁潸然泪下！再见了，奥布之魂！</d>
<d p="0,1,25,16777215,1492058958,0,b109104e,3218625782">这集也是经典啊</d>
<d p="1136.5200195312,1,25,16777215,1492060120,0,b109104e,3218695244">经典啊！！！QAQ</d>
<d p="1269.3900146484,1,25,16777215,1492060253,0,b109104e,3218703044">233333333333333</d>
<d p="1314,1,25,16777215,1492060297,0,b109104e,3218705700">真男人！QAQ</d>
<d p="61.659000396729,1,25,16777215,1492067078,0,891c287d,3218975304">20170413</d>
<d p="1336.3299560547,5,25,16711680,1492089734,0,5b7fbd8f,3220171374">曙光社和质量加速炸了 地球军这次也算是几乎白来</d>
<d p="309.65701293945,1,25,16777215,1492091248,0,83fa7fa1,3220282910">永远不用阴阳炮的大天使号，用了估计就可以提前结局了</d>
<d p="376.85101318359,1,25,16777215,1492091366,0,83fa7fa1,3220292204">所以说自由和正义其实都是加点太极端的机体，一个全点近战一个全点远程</d>
<d p="565.04602050781,1,25,16777215,1492091613,0,83fa7fa1,3220310778">不不不，议长如果知道连儿子都叛变的话怕是要飞升哦</d>
<d p="740.78497314453,1,25,16777215,1492091839,0,83fa7fa1,3220328052">主要是现在两主角都不打驾驶室，不然像以前那样下死手早收工了</d>
<d p="762.49798583984,1,25,16777215,1492091888,0,83fa7fa1,3220331868">永久是不行的，动力够但硬件会坏</d>
<d p="840.02697753906,1,25,16777215,1492091988,0,83fa7fa1,3220339974">然后就成了第二部的最强第三方？</d>
<d p="919.25897216797,1,25,16777215,1492092127,0,83fa7fa1,3220350858">终于想起来大天使号的必杀武装了，刚刚为什么不用啊</d>
<d p="1006.200012207,1,25,16777215,1492092259,0,83fa7fa1,3220361200">红字你这个思想很危险，上一个这么质疑基神的已经凉了</d>
<d p="1065.2900390625,1,25,16777215,1492092394,0,83fa7fa1,3220371762">空中战都不适合风暴了，你还指望几乎不会飞的完美出击啊</d>
<d p="1174.8499755859,1,25,16777215,1492092542,0,83fa7fa1,3220383406">知道真相的基神整个人都懵逼了</d>
<d p="371.58599853516,1,25,16777215,1492098398,0,d09fdf76,3220837872">我去，火力无限啊</d>
<d p="275.89199829102,1,25,16777215,1492153994,0,4a3ec080,3222451074">刚刚闪灯拿一下</d>
<d p="1319.7600097656,1,25,16777215,1492155041,0,4a3ec080,3222490710">真男人</d>
<d p="909.88397216797,1,25,16777215,1492171727,0,25c0aa5c,3223506210">我去，平板撑</d>
<d p="906.62701416016,1,25,16777215,1492171765,0,25c0aa5c,3223509204">我去，平板撑</d>
<d p="1137.6899414062,1,25,16777215,1492179659,0,9371aae0,3224243024">好怀念的歌曲</d>
<d p="1338.7800292969,1,25,16777215,1492186948,0,57e63c4d,3224896202">奥布雄狮！</d>
<d p="1118.2299804688,1,25,16777215,1492188030,0,234768ab,3224961670">专听神曲</d>
<d p="1152.8100585938,1,25,16777215,1492188068,0,234768ab,3224963740">胡志明</d>
<d p="1328.0500488281,1,25,16777215,1492188267,0,234768ab,3224975192">核平的奥布</d>
<d p="1023.950012207,1,25,16777215,1492189563,0,5e305ae3,3225046750">后面给了穆</d>
<d p="244.31500244141,1,25,16777215,1492199224,0,e5ade0fe,3225285094">前面棺材店老板的，你知道棺材店老板的媳妇要生了吗</d>
<d p="631.67700195312,1,25,16777215,1492227730,0,2c284cf5,3226126654">我去以前没看出来啊</d>
<d p="411.23599243164,1,25,16777215,1492232552,0,513a074b,3226476786">+1</d>
<d p="531.22900390625,1,25,16777215,1492237291,0,89598c75,3226835314">不对？  到底是对还是不对?←_←</d>
<d p="96.244003295898,1,25,16777215,1492243852,0,50ff007c,3227262222">作，继续作</d>
<d p="604.82598876953,1,25,16777215,1492256891,0,9a22ce14,3228259866">结果这两个在一起了？</d>
<d p="461.38598632812,1,25,16777215,1492261582,0,b3c93fa6,3228674720">混合双打hhhhh</d>
<d p="835.73602294922,1,25,16777215,1492266101,0,20ed196a,3229134908">不不 翻译没错……</d>
<d p="732.14697265625,1,25,16777215,1492275805,0,4dd0215b,3229992804">虚晃一刀掉头就跑。</d>
<d p="1028.4499511719,1,25,16777215,1492276088,0,6541313c,3230016776">穆叔恢复记忆专用</d>
<d p="389.85000610352,1,25,16777215,1492307242,0,b1dc4ca6,3230885686">因为还有个神意高达是全属性啊</d>
<d p="536.2490234375,1,25,16777215,1492332521,0,826744f1,3232938716">不对。2333333</d>
<d p="442.51300048828,1,25,16777215,1492333273,0,f0f01b7b,3232997540">打偏就神作</d>
<d p="175.7859954834,1,25,16777215,1492334728,0,7b0bf2f0,3233111376">第一‍♂️</d>
<d p="1385.4200439453,1,25,16777215,1492336993,0,0a27e78a,3233286144">拉斯提不是海涅</d>
<d p="1183.9399414062,1,25,16777215,1492340165,0,ae8691b9,3233530654">有情人终须是兄妹</d>
<d p="1110.1999511719,1,25,16777215,1492352573,0,69cdc309,3234548770">把大气层给轰开了，减小了空气阻力</d>
<d p="442.10101318359,1,25,16777215,1492354881,0,81f938e2,3234804416">justice的大背包好累赘啊～</d>
<d p="1247.3900146484,1,25,16777215,1492356921,0,d781d1d0,3234969562">说的对红色有角三倍速</d>
<d p="1258.2900390625,1,25,16777215,1492404191,0,da44539e,3236127728">正义手上的盾牌突然没了</d>
<d p="246.52600097656,1,25,16777215,1492408342,0,ad584e17,3236367184">需要按他老人家的棺材板的人手也严重不足了，所以……</d>
<d p="569.21697998047,1,25,16777215,1492408764,0,ad584e17,3236383562">幸好是看到几乎会背台词的程度，不然这台词真的……</d>
<d p="1221.9100341797,1,25,16777215,1492408912,0,5c8459d7,3236389230">正义有小飞机阿</d>
<d p="1403.9399414062,1,25,16777215,1492409608,0,ad584e17,3236413768">换妻结束</d>
<d p="411.89099121094,1,25,16777215,1492423982,0,d8564519,3237014608">神意 进远都厉害</d>
<d p="48.570999145508,1,25,41194,1492436744,0,e6160b7d,3237832264">2018 7 28</d>
<d p="206.32499694824,1,25,16777215,1492440753,0,4dd58745,3238140750">战争极端起来，什么不科学的武器都会出现~</d>
<d p="292.21899414062,1,25,16777215,1492441976,0,2bed3a00,3238235536">红衣跳槽系列</d>
<d p="513.47302246094,1,25,16777215,1492442300,0,2bed3a00,3238260728">拂晓给她了估计要让火神炮日下来</d>
<d p="728.89202880859,1,25,16777215,1492442527,0,2bed3a00,3238277680">主角光环就是能量无限的意思- -</d>
<d p="747.52197265625,1,25,16777215,1492442554,0,2bed3a00,3238279702">这会要是有龙骑兵不知道是什么效果</d>
<d p="851.80200195312,1,25,16777215,1492442665,0,2bed3a00,3238287936">收拾收拾传火了</d>
<d p="1006.2399902344,1,25,16777215,1492442761,0,2bed3a00,3238302342">知道也没用 拂晓这个时候出场会被虐</d>
<d p="1034.9200439453,1,25,16777215,1492442909,0,2bed3a00,3238306248">攒钱造给卡嘉莉的 最后给穆叔了</d>
<d p="1220.1999511719,1,25,16777215,1492443103,0,2bed3a00,3238322750">正义这个时候所有机体里最快的你跟我说自由？</d>
<d p="1334.6800537109,1,25,16777215,1492443242,0,2bed3a00,3238333134">轨道炸了都不给你用系列</d>
<d p="54.332000732422,5,25,16777215,1492443411,0,d0183d3b,3238346500">没有人觉得这段超帅吗？</d>
<d p="132.05000305176,5,25,16777215,1492443443,0,d0183d3b,3238349084">不跳op我自豪</d>
<d p="138.14999389648,5,25,16777215,1492443459,0,d0183d3b,3238350394">自由和正义好帅啊</d>
<d p="261.70999145508,5,25,16777215,1492443606,0,d0183d3b,3238361858">思想钢印233333</d>
<d p="1121.0500488281,1,25,15138834,1492444566,0,d0183d3b,3238439124">晓之车上线！</d>
<d p="1403.9899902344,5,25,15138834,1492444972,0,d0183d3b,3238460498">拉克丝的腿那是被裙子挡住了。。。。</d>
<d p="1263.2900390625,1,25,16777215,1492491879,0,c2b41a5e,3239495548">基出新境界</d>
<d p="758.15399169922,1,25,65280,1492495135,0,69f34700,3239654054">当然是原谅她咯</d>
<d p="81.249000549316,1,25,16777215,1492523664,0,dad42813,3241219404">20170418</d>
<d p="608.57897949219,5,25,9487136,1492525478,0,f1416acb,3241363056">还有对人♂射</d>
<d p="1009.8599853516,5,25,15138834,1492525916,0,f1416acb,3241398282">这个画面已经出现三次了...每次出场都是这个，经费烧光了？</d>
<d p="706.90399169922,1,25,16777215,1492528722,0,af941669,3241637434">记住这一炮</d>
<d p="1316.3299560547,1,25,16777215,1492530172,0,1912f4cb,3241744102">自爆第一人</d>
<d p="1413,1,25,16777215,1492530269,0,1912f4cb,3241750874">海涅大他们一届</d>
<d p="758.84497070312,1,25,16777215,1492566014,0,35387f25,3242561436">地球圈里用龙骑兵？</d>
<d p="981.36602783203,1,25,16777215,1492567521,0,94a63536,3242598798">原来你想跟认识的人战斗啊</d>
<d p="394.60699462891,1,25,16777215,1492576378,0,1379d0f1,3242907478">是神谕高达</d>
<d p="759.291015625,1,25,16777215,1492576773,0,1379d0f1,3242931794">ntd:龙骑兵？ 不存在的</d>
<d p="845.32702636719,1,25,16777215,1492578636,0,3e100cfc,3243061692">不一定是大天使走哪那就打仗吧 那都在打仗</d>
<d p="872.458984375,1,25,16777215,1492578663,0,3e100cfc,3243063466">父亲：你别搞她啊</d>
<d p="1091.7700195312,1,25,16777215,1492578930,0,83176364,3243080384">我可是为了看这一幕才一直看到这里的</d>
<d p="1132.9000244141,1,25,16777215,1492578971,0,83176364,3243082712">神曲的正确用法</d>
<d p="1014.9099731445,1,25,15138834,1492579037,0,2ad549ef,3243086592">拂晓先卡嘉丽的专用机，后来给修叔了。</d>
<d p="1257.1300048828,1,25,16777215,1492579047,0,3e100cfc,3243087272">这画面...</d>
<d p="1313.5999755859,1,25,16777215,1492579104,0,3e100cfc,3243090524">又是炸弹...</d>
<d p="1433.6300048828,1,25,16777215,1492579224,0,3e100cfc,3243097676">阿斯兰怕什么 那是姐弟- -</d>
<d p="672.36297607422,1,25,16777215,1492580568,0,bf97d59a,3243169332">厉害了我的兰</d>
<d p="1049.0600585938,1,25,16777215,1492580743,0,bf97d59a,3243177158">这喷射器好厉害...</d>
<d p="1317.5899658203,1,25,16777215,1492581010,0,bf97d59a,3243189292">真男人！！！</d>
<d p="1341.3599853516,1,25,16777215,1492581034,0,bf97d59a,3243190364">直接把轨道炸了！！！</d>
<d p="1040.75,1,25,15138834,1492588322,0,80c2d1b9,3243441940">一架拂晓的钱够造十架异端了</d>
<d p="1265.3199462891,1,25,16777215,1492597127,0,6d554a63,3243843860">十指相印，双目对视</d>
<d p="564.87200927734,1,25,16777215,1492599506,0,ad7f3355,3244039510">他不会高兴的</d>
<d p="386.99499511719,1,25,16777215,1492602697,0,0028483c,3244254788">正好互补嘛</d>
<d p="479.51501464844,1,25,16777215,1492602820,0,0028483c,3244262464">flag</d>
<d p="1186.4899902344,1,25,16777215,1492603727,0,0028483c,3244325902">卡嘉莉又被关门里了2333</d>
<d p="1248.1899414062,1,25,16777215,1492603795,0,0028483c,3244330824">哈哈哈哈哦基佬笑死我了</d>
<d p="1257.8100585938,5,25,15138834,1492603810,0,0028483c,3244331956">囍</d>
<d p="1307.0600585938,5,25,16777215,1492603869,0,0028483c,3244336030">我敬你是条汉子</d>
<d p="1296.5999755859,1,25,65535,1492621946,0,f0bf5223,3245616626">可惜老父亲了</d>
<d p="54.534999847412,1,25,16777215,1492623514,0,4c4a0f52,3245661276">20170420</d>
<d p="1093.0799560547,1,25,16777215,1492624573,0,4c4a0f52,3245686304">所以第二季卡嘉莉背负重任</d>
<d p="1309.1999511719,1,25,16777215,1492624824,0,4c4a0f52,3245691786">奥布之狮，走好</d>
<d p="1368.0200195312,1,25,16777215,1492624897,0,4c4a0f52,3245693212">对，三周目不亏</d>
<d p="265.62298583984,1,25,16777215,1492672231,0,0cbb95ce,3247340778">两台S打3台A  怎么打怎么都有优势</d>
<d p="1126.1800537109,1,25,16777215,1492681382,0,f3136b65,3247750596">神曲上线</d>
<d p="12.180999755859,1,25,16777215,1492683970,0,a030d891,3247903666">沈氏空降兵</d>
<d p="303.39001464844,1,25,16777215,1492684214,0,a030d891,3247918382">迪亚哥：“我只是为了个妹子而已。”</d>
<d p="1097.7099609375,1,25,16777215,1492685039,0,a030d891,3247968738">这集我哭了????</d>
<d p="1320.6099853516,1,25,16777215,1492685271,0,a030d891,3247984094">真男人，奥布之师</d>
<d p="138.75799560547,1,25,16777215,1492699811,0,57934f28,3249059754">me too</d>
<d p="1326.8199462891,1,25,16777215,1492699897,0,fdb0f9e0,3249066794">沉迷自爆。</d>
<d p="242.60000610352,1,25,16777215,1492699916,0,57934f28,3249068222">我也忙啊</d>
<d p="358.75399780273,1,25,16777215,1492700136,0,57934f28,3249086292">往上？</d>
<d p="990.96398925781,1,25,16777215,1492701197,0,57934f28,3249172766"> 服</d>
<d p="1156.1600341797,1,25,16777215,1492701442,0,57934f28,3249192860">不是已经走了吗</d>
<d p="751.95202636719,1,25,15138834,1492705574,0,cd674cf2,3249519768">龙骑兵大气层里用不了，没有动力飞起来的</d>
<d p="926.57897949219,1,25,15138834,1492705651,0,cd674cf2,3249523174">那东西会污染，大天使不会用的</d>
<d p="1287.0899658203,1,25,15138834,1492705862,0,cd674cf2,3249534210">前面的，自由只有五发，正义三发</d>
<d p="555.04498291016,1,25,16777215,1492724550,0,91024c32,3249880770">少见？自由是你们自己研发的机体啊虽然没有驾驶员成分上去</d>
<d p="52.67200088501,1,25,16777215,1492769728,0,4da16b1f,3251645646">神OP</d>
<d p="135.93200683594,1,25,16777215,1492769807,0,4da16b1f,3251652468">+1</d>
<d p="1266.9300537109,1,25,16777215,1492771107,0,4da16b1f,3251761396">好帅！</d>
<d p="1304.6300048828,1,25,16777215,1492771258,0,4da16b1f,3251779184">都是和</d>
<d p="1306.4499511719,1,25,16777215,1492771282,0,4da16b1f,3251781104">善的眼神！</d>
<d p="1369.1800537109,1,25,16777215,1492771516,0,4da16b1f,3251798682">炸了！</d>
<d p="1404,1,25,16777215,1492771664,0,4da16b1f,3251802642">真-神•CP</d>
<d p="419.94400024414,1,25,16777215,1492780987,0,ffc6e70b,3252702826">不不不，，大气圈用不了龙骑兵啊，神意大气圈飞起来都费劲感觉</d>
<d p="677.84997558594,1,25,16777215,1492781307,0,ffc6e70b,3252731870">讲真三小强已经非常强了，电池机打核能机而且对面是两个挂壁</d>
<d p="1215,1,25,16777215,1492782159,0,4eef75a2,3252812516">好怀念啊</d>
<d p="779.02001953125,1,25,16777215,1492782784,0,4da16b1f,3252873230">扎多-命运  地球-自由  噢布-正义</d>
<d p="1275.6999511719,1,25,16777215,1492827440,0,2ea92605,3254673968">盾又出现了</d>
<d p="999.166015625,1,25,16777215,1492839333,0,f2b299f6,3255525066">拂晓现在只完成了机体，配套武器跟不上，战斗力不一定强</d>
<d p="1033.8100585938,1,25,16777215,1492839397,0,f2b299f6,3255530124">原版bgm从这里开始唱了</d>
<d p="1119.1300048828,1,25,16737894,1492839488,0,f2b299f6,3255537294">除了“晓之车”，怎么还有奇怪的bgm混进来了。。。</d>
<d p="1199.7700195312,1,25,16737894,1492839630,0,f2b299f6,3255548778">哈奥米亚神与我们同在！悲壮！！</d>
<d p="1311.4000244141,1,25,16777215,1492843884,0,d908d7ba,3255900016">敬你是条汉子！</d>
<d p="298.2080078125,1,25,16707842,1492849075,0,3aa12733,3256251656">似乎达成了共识。</d>
<d p="1378.1500244141,1,25,16777215,1492854105,0,aa6a0215,3256620488">黄昏的魔弹</d>
<d p="58.596000671387,5,25,16777215,1492854936,0,5f0ed2f9,3256693764">看完这段就跳2333</d>
<d p="252.58200073242,1,25,16777215,1492868139,0,a3700af6,3257828552">笔记</d>
<d p="1099.0600585938,1,25,16777215,1492870364,0,c0a7726d,3258084600">晓之车</d>
<d p="372.53799438477,1,25,16777215,1492872113,0,7a344337,3258262028">橡胶机关枪！！！</d>
<d p="400.51901245117,1,25,16777215,1492872175,0,7a344337,3258268012">说神谕的，神谕有浮游炮的</d>
<d p="894.13299560547,1,25,16777215,1492881332,0,6b745e07,3259070510">叁艦聯盟上線中</d>
<d p="1115.2399902344,1,25,16776960,1492889272,0,984b9c6e,3259379018">神bgm</d>
<d p="259.24798583984,5,25,15138834,1492912876,0,3212bae8,3259996880">拉克丝.克莱茵————拯救世界的女人</d>
<d p="595.56402587891,1,25,16777215,1492915193,0,c0eaf28b,3260155326">小伊去了  2小强就没了</d>
<d p="929.55401611328,1,25,16777215,1492915561,0,c0eaf28b,3260183316">开始说了会污染地球 还有就是用阳电子打MS？你想学第二部被基神打爆</d>
<d p="560.84802246094,1,25,16777215,1492938507,0,34ad3361,3262079460">机密呗</d>
<d p="1147.5400390625,1,25,16777215,1492938990,0,18137112,3262117970">每天一次  是真的好听啊！！！ </d>
<d p="115.37000274658,5,25,41194,1492939727,0,a6e2a330,3262177314">MG要出正义了( ˘•ω•˘ )</d>
<d p="279.1669921875,1,25,16777215,1492944111,0,51bf05d4,3262526070">你是才看见他是吗。。。</d>
<d p="263.84201049805,1,25,16777215,1492964027,0,f1403425,3264178254">死一个还有2个在奥布，可怜的伊扎克</d>
<d p="287.51400756836,1,25,65280,1492964671,0,2cd7a392,3264215942">才发现</d>
<d p="1159.3199462891,1,25,65280,1492965145,0,2cd7a392,3264241308">骨科</d>
<d p="1292.9399414062,1,25,16777215,1492971632,0,913659f8,3264455178">他们不敢打坏轨道啊</d>
<d p="1316.7299804688,1,25,16777215,1492974843,0,94a308a2,3264506674">那么问题来了，拂晓去哪了，也被炸了吗？</d>
<d p="139.13900756836,1,25,16777215,1492987256,0,3f063ee6,3264615658">+2</d>
<d p="115.08399963379,1,25,16777215,1493003596,0,0e14956d,3265079130">2017424</d>
<d p="187.35000610352,1,25,15138834,1493004062,0,7d5e38c1,3265092894">本来就不科学 但是我喜欢看啊 何必当真</d>
<d p="885.64801025391,5,25,16707842,1493022662,0,c0ea8782,3265950676">为什么全是女的</d>
<d p="733.65002441406,1,25,16777215,1493027307,0,2054acad,3266158252">核动力的就是爽</d>
<d p="762.48999023438,1,25,16777215,1493027336,0,2054acad,3266159786">龙骑兵只能宇宙用吧？</d>
<d p="1314.1099853516,1,25,16777215,1493029848,0,2054acad,3266307732">泪目</d>
<d p="478.14801025391,1,25,16777215,1493031720,0,461ea9e3,3266436768">↓把这艘船打爆就直接GG了</d>
<d p="1355.0200195312,1,25,16777215,1493040635,0,d0e6266a,3267064994">拉女神这身真漂亮，不过不是第二季的图么</d>
<d p="1364.4100341797,1,25,16777215,1493040684,0,d0e6266a,3267067920">看到这张更确定了，第二季的ed图吧</d>
<d p="1378.8299560547,1,25,16777215,1493040621,0,d0e6266a,3267070724">海涅</d>
<d p="999.06201171875,1,25,16777215,1493042633,0,101e670a,3267224184">阿斯蘭:好，我和你走，但是你姐以後必須睡服我。基拉:好。233333</d>
<d p="724.48400878906,1,25,16777215,1493042753,0,26d34c5d,3267233248">这三小强没有ps装甲的吗</d>
<d p="1253.0699462891,1,25,16777215,1493042941,0,101e670a,3267248786">哦，倆基佬。。。別跑23333</d>
<d p="615.89099121094,1,25,15138834,1493048176,0,750b2ac3,3267677280">贞操带的锁</d>
<d p="1245.0500488281,1,25,16777215,1493057403,0,7c4af82f,3268094468">记忆犹新啊</d>
<d p="157.50199890137,1,25,16777215,1493063269,0,47069969,3268173780">这个是菊花嘴。，，，，，</d>
<d p="623.19201660156,1,25,16777215,1493063797,0,47069969,3268178588">，，，，，，</d>
<d p="1325.5799560547,1,25,16777215,1493064436,0,47069969,3268183954">拂晓在那啥工厂里藏着</d>
<d p="1396.1300048828,1,25,16777215,1493064529,0,47069969,3268184738">海涅是第二季的克隆人</d>
<d p="875.43402099609,1,25,16777215,1493089846,0,f6f878c4,3268572952">草薙</d>
<d p="653.59197998047,1,25,16777215,1493092337,0,910ae30d,3268656258">怎么还不爆种啊…</d>
<d p="1176.6300048828,1,25,16777215,1493092814,0,910ae30d,3268672974">是弟弟啊喂</d>
<d p="1079.3100585938,1,25,16777215,1493109037,0,582527c5,3269395894">原版的晓之车都开始啦</d>
<d p="17.22500038147,1,25,16777215,1493117710,0,bc1ac434,3269896024">晓之车</d>
<d p="9.0740098953247,1,25,16777215,1493117728,0,ac91d047,3269897184">来听歌</d>
<d p="1322.8900146484,1,25,16777215,1493118153,0,ac91d047,3269924630">前面的，拂晓早就留好了，在地下</d>
<d p="1330.0200195312,1,25,16777215,1493118181,0,ac91d047,3269926500">炸了曙光社总部和辉夜轨道</d>
<d p="385.2619934082,5,25,16711935,1493122828,0,178b4301,3270247734">BGM：恶之三兵器    算是我很喜欢的一首了  seed里</d>
<d p="396.26901245117,5,25,6697728,1493122871,0,178b4301,3270250914">神域不是全属性的  当初开发出来是作为重装近战特化机来用的 </d>
<d p="397.66000366211,5,25,6697728,1493122911,0,178b4301,3270253604">只是在雅金杜维前克队强行要求把没有开发完成的龙骑兵系统装上去的而已</d>
<d p="384.70300292969,1,25,16777215,1493123752,0,dc147523,3270312982">注意：这是三小强的BGM！！基神在这BGM里是赢不了的！</d>
<d p="65.109001159668,1,25,16777215,1493132533,0,5b74374f,3270999912">20170425</d>
<d p="24.754999160767,1,25,16777215,1493178706,0,6d3e6dd0,3272197324">儿时印象最深的晓之车！</d>
<d p="1307.9000244141,1,25,16777215,1493198594,0,8e6e2e60,3273350730">为什么不走多点老种子啊</d>
<d p="187.01600646973,1,25,16777215,1493199289,0,52087b87,3273385504">说科学的，难道魔法少女就科学了吗？</d>
<d p="660.27001953125,1,25,16777215,1493200450,0,8a575cbc,3273499298">基拉、阿斯兰：导演不让我也很绝望啊</d>
<d p="4.6609997749329,1,25,16777215,1493200671,0,e1c68184,3273512198">晓之车上线</d>
<d p="277.89300537109,1,25,16777215,1493200953,0,e1c68184,3273529296">233333对面有布机 有点压力</d>
<d p="370.5530090332,1,25,16777215,1493201054,0,e1c68184,3273535384">无双割草233</d>
<d p="417.04800415039,1,25,16777215,1493201110,0,e1c68184,3273539002">真TM帅233</d>
<d p="665.97497558594,1,25,16777215,1493201364,0,e1c68184,3273554908">233</d>
<d p="961.48602294922,1,25,16777215,1493201660,0,e1c68184,3273573266">经典场景准备上映</d>
<d p="1012.3499755859,1,25,16777215,1493201722,0,e1c68184,3273577348">一如既往的熟悉的画面233</d>
<d p="1120.8699951172,1,25,16777215,1493201840,0,e1c68184,3273584806">神曲上线</d>
<d p="1218.3199462891,1,25,16777215,1493201946,0,e1c68184,3273591736">这一幕好怀念</d>
<d p="1278.6500244141,1,25,16777215,1493202029,0,e1c68184,3273597022">感觉 重置版 没有当初TV版这一幕感人</d>
<d p="1384.6800537109,1,25,16777215,1493202137,0,e1c68184,3273603908">海涅233</d>
<d p="364.18600463867,1,25,16777215,1493209631,0,2ee45224,3274118660">rengunwang</d>
<d p="45.757999420166,1,25,16777215,1493215417,0,67b8d1f0,3274555656">真可怜一句台词三个人分</d>
<d p="779.70501708984,1,25,16777215,1493216101,0,67b8d1f0,3274612626">终于有人吐槽这个翻译了。胡子密 胡子希怎么办2333</d>
<d p="1086.1099853516,1,25,16777215,1493216376,0,67b8d1f0,3274635966">脑补开始版</d>
<d p="343.96200561523,1,25,16777215,1493218031,0,ee352f5f,3274778058">上一代的旗舰机这就变炮灰了啊</d>
<d p="409.5119934082,1,25,16777215,1493218111,0,ee352f5f,3274784678">3小强刚登场怎么也要风光一下嘛</d>
<d p="1176.2399902344,1,25,16777215,1493220752,0,f6638872,3274993690">是弟弟，前面的</d>
<d p="1147.4300537109,1,25,16777215,1493221620,0,6b863617,3275054216">这bgm真的好</d>
<d p="323.37100219727,1,25,16777215,1493229061,0,919551f2,3275369706">电阳子炮在地球很难冷却所以不用</d>
<d p="1292.5899658203,1,25,16777215,1493230773,0,a696c945,3275402606">走好</d>
<d p="1321.7800292969,1,25,16777215,1493230807,0,a696c945,3275403264">走好</d>
<d p="1170.8699951172,1,25,16777215,1493248458,0,3d15025e,3275571994">扎心了。。。。</d>
<d p="525.96002197266,1,25,16777215,1493263348,0,bd361876,3275900666">说火神炮的别走，笑死了????</d>
<d p="1131.8699951172,1,25,16777215,1493263693,0,bbe042a6,3275911516">原版插这么早也不好吧，这里开始作战了才响BGM可以啊</d>
<d p="610.77899169922,1,25,16777215,1493267992,0,6d09be0f,3276112126">克队速度好快</d>
<d p="1116.9699707031,1,25,16777215,1493268568,0,6d09be0f,3276149464">啊啊啊啊，神曲上线了</d>
<d p="1125.4499511719,1,25,16777215,1493268595,0,6d09be0f,3276151058">晓之车！！！！！！</d>
<d p="1206.5300292969,1,25,16777215,1493268698,0,6d09be0f,3276157640">神与你们同在</d>
<d p="1271.7900390625,1,25,16777215,1493268776,0,6d09be0f,3276162620">帅炸了！！！！！！</d>
<d p="1337.7299804688,1,25,16777215,1493268886,0,6d09be0f,3276170020">烈火中的雄狮！！！！！！</d>
<d p="241.66400146484,1,25,16777215,1493273254,0,b17d21ef,3276399854">前面说棺材店的老板恨忙那个 你知道棺材木匠工好忙的好吗？</d>
<d p="766.69299316406,1,25,16777215,1493307359,0,a4c53c1a,3278397282">NTD是最不怕精神兵器的</d>
<d p="1059.7900390625,1,25,16777215,1493307418,0,a4c53c1a,3278413814">缪叔要出击了以强袭的性能绝对回不去的</d>
<d p="196.09199523926,1,25,16777215,1493314656,0,ec1590b2,3278767576">也不一定不科学啊，只是现在的科学解释不了吧，未来说不定真有</d>
<d p="722.84698486328,1,25,16777215,1493315183,0,ec1590b2,3278781658">因为这机甲很强了暂时还用不到爆种</d>
<d p="746.25299072266,1,25,16777215,1493315225,0,ec1590b2,3278782698">惊现越前龙马名句2333333</d>
<d p="1310.6600341797,1,25,15138834,1493356290,0,a643ca6e,3279762040">再见</d>
<d p="925.52197265625,1,25,16777215,1493361388,0,d977e877,3280030924">因为阳电子炮对环境有很大伤害</d>
<d p="1377.3399658203,1,25,16777215,1493361835,0,d977e877,3280050060">我也超喜欢拉克丝！</d>
<d p="485.31500244141,1,25,16777215,1493386005,0,9eacd819,3281799862">大天使号其实是有能力左右战局的一艘船，但就是死活不用阳电子炮</d>
<d p="12.178999900818,1,25,16777215,1493409661,0,0cb4430c,3283255878">这集当年看得感动啊！</d>
<d p="1246.1999511719,1,25,16777215,1493448938,0,bf97d59a,3285130798">yooooooooooooooooooo</d>
<d p="496.49398803711,1,25,16777215,1493450966,0,fe90b4db,3285276102">指挥舰躲得远远的</d>
<d p="673.86401367188,1,25,16777215,1493451036,0,fe90b4db,3285281026">哈哈哈哈到你没蓝了</d>
<d p="870.42401123047,1,25,16777215,1493451232,0,fe90b4db,3285294848">新装备？</d>
<d p="252.09599304199,1,25,16777215,1493463352,0,d1786b89,3286235202"> 前面棺材店老板老婆快生的那个你知道他们已经生了吗</d>
<d p="885.76800537109,1,25,16777215,1493476228,0,fef9534e,3287494406">耻球军妹</d>
<d p="1138.8199462891,1,25,16777215,1493476774,0,b638bb23,3287553670">神曲上线</d>
<d p="1228.1500244141,1,25,16777215,1493476863,0,b638bb23,3287563088">每次看待这一幕都很感动</d>
<d p="1323.9100341797,1,25,16777215,1493476957,0,b638bb23,3287572730">真男人</d>
<d p="465.79598999023,1,25,16777215,1493483080,0,88105763,3288159112">为啥我开始同情地球军了23333</d>
<d p="597.80700683594,1,25,16777215,1493483237,0,88105763,3288171764">议长知道他儿子在里面会犯高血压的</d>
<d p="70.893997192383,1,25,16777215,1493486324,0,158c17e2,3288408404">2017 04 30</d>
<d p="206.3990020752,1,25,16777215,1493494839,0,c7fd5d0f,3288747078">牛顿也不是不能被推翻的吧</d>
<d p="303.08200073242,1,25,16777215,1493494953,0,c7fd5d0f,3288749224">迪亚哥:计划通</d>
<d p="1012.4299926758,1,25,16777215,1493537068,0,14934bb5,3291134302">这句话好像那个回来过圣诞节一样</d>
<d p="230.71800231934,1,25,16777215,1493540343,0,cba45675,3291410144">前面牛顿忙的，牛顿是在忙着推棺材板</d>
<d p="319.36801147461,1,25,16777215,1493557858,0,aa6aa0b6,3293134212">黄毛flag</d>
<d p="681.23797607422,1,25,16777215,1493565574,0,dc9f5253,3294043138">这部高达血蓝一体没蓝就没血了</d>
<d p="816.07598876953,1,25,16777215,1493565727,0,dc9f5253,3294060826">帕克里克萨拉，是阿斯兰他爹</d>
<d p="949.87902832031,1,25,16777215,1493565882,0,dc9f5253,3294080534">要是乌兹米没那么傲娇，卡嘉莉也不会被逼的嫁紫菜头</d>
<d p="482.3869934082,1,25,16777215,1493571889,0,d172af69,3294633258">一口毒奶</d>
<d p="138.56199645996,1,25,16777215,1493594072,0,56fb66be,3295191192">＋1</d>
<d p="208.06100463867,1,25,16776960,1493603666,0,c3416513,3295675330">牛顿看到动漫 经常掀棺材板</d>
<d p="275.31600952148,1,25,16776960,1493603770,0,c3416513,3295683630">这里阿斯兰才知道迪亚哥原来也在这里 所以语气很惊讶</d>
<d p="287.23498535156,5,25,16776960,1493603816,0,c3416513,3295687098">迪亚哥脑壳就是比较灵活点 套路阿斯兰</d>
<d p="297.98599243164,1,25,16776960,1493603835,0,c3416513,3295688544">23333333333333333</d>
<d p="368.73599243164,1,25,16776960,1493603921,0,c3416513,3295695258">这骚的 23333333333</d>
<d p="389.92498779297,1,25,16776960,1493603969,0,c3416513,3295699060">这里基神还是打得贼吃力</d>
<d p="411.51300048828,1,25,16776960,1493604005,0,c3416513,3295701914">阿斯兰又来救基拉了</d>
<d p="443.96600341797,1,25,16776960,1493604054,0,c3416513,3295705664">哈哈 迪亚哥真是拼呀</d>
<d p="609.47698974609,1,25,16776960,1493604289,0,c3416513,3295725350">举第三条腿也能解决</d>
<d p="653.32598876953,1,25,16776960,1493604375,0,c3416513,3295732388">阿斯兰装备多就是好</d>
<d p="683.83099365234,1,25,16776960,1493604420,0,c3416513,3295736084">阿斯兰还是贼厉害</d>
<d p="1043,1,25,16776960,1493604946,0,c3416513,3295780094">哈哈 不让暴风出场</d>
<d p="1123.9799804688,1,25,16776960,1493605065,0,c3416513,3295791348">神曲来了</d>
<d p="1166,1,25,16776960,1493605142,0,c3416513,3295797930">卡嘉莉：纳尼 我跟他又暧昧的人居然是我哥哥</d>
<d p="1263.4200439453,5,25,16776960,1493605318,0,c3416513,3295812892">基佬画面！！</d>
<d p="1272.4799804688,1,25,16776960,1493605350,0,c3416513,3295815474">哈哈 吓都把别人吓死了</d>
<d p="1361.5500488281,5,25,16776960,1493605495,0,c3416513,3295828120">卡嘉莉女神也是美得不行</d>
<d p="1376.9599609375,1,25,16776960,1493605532,0,c3416513,3295831400">这是哪些娃儿？</d>
<d p="1380.1899414062,1,25,16776960,1493605553,0,c3416513,3295833208">迪亚哥这表情 233333333333</d>
<d p="1388.0899658203,5,25,16776960,1493605600,0,c3416513,3295837228">这画面 2333333333</d>
<d p="1399.9699707031,5,25,16776960,1493605757,0,c3416513,3295850244">换妻结束</d>
<d p="1403.4100341797,1,25,16776960,1493605797,0,c3416513,3295853584">半透明的情趣衣 我喜欢</d>
<d p="610.60998535156,1,25,16777215,1493626934,0,82f7aca9,3297477558">成为另一个人的减压炮了</d>
<d p="1005.9699707031,1,25,16777215,1493633884,0,f8b689b6,3298088198">想多了，一台机体罢了</d>
<d p="1347.7099609375,1,25,16777215,1493635432,0,e137ed11,3298223558">无论如何，seed十五年后的我因为听了七八年晓之车而第一次看，真的很感动</d>
<d p="598.78302001953,1,25,16777215,1493642939,0,96b75e8f,3298886618">事后</d>
<d p="1226.3599853516,1,25,16777215,1493644043,0,11f64f2d,3298992184">当初看的时候紧张的不行，以为牵手失败</d>
<d p="40.112701416016,1,25,16777215,1493644547,0,1840e043,3299039668">专程来听晓之车</d>
<d p="702.20697021484,1,25,16777215,1493645842,0,1840e043,3299166064">2333333333</d>
<d p="1165.4599609375,1,25,16777215,1493646682,0,1840e043,3299247618">暴击</d>
<d p="140.64599609375,1,25,16777215,1493656187,0,c9212318,3300131880">+1</d>
<d p="201.55299377441,1,25,16777215,1493656468,0,c9212318,3300143256">就好像一百年前，不，二战末期的人想象得到现在的生活景象吗？</d>
<d p="734.90399169922,1,25,16777215,1493656509,0,a2dda5fc,3300145946">其实应该换人打吧。。</d>
<d p="203.32400512695,1,25,16777215,1493656543,0,c9212318,3300148082">现在一块智能手表就相当于占了一整个房间大小的第一台计算机的计算力了</d>
<d p="354.71200561523,1,25,16777215,1493656775,0,8d29c734,3300162444">骁龙821和骁龙835你说谁厉害</d>
<d p="544.04602050781,1,25,16777215,1493658789,0,833f3bdf,3300266962">我知道了  这不是翻译的这是找同音字的</d>
<d p="854.80999755859,1,25,16777215,1493704234,0,c34eaec4,3301486878">上去送！我来传火</d>
<d p="448.43798828125,1,25,16777215,1493709448,0,262e20bc,3301699834">那个是飞行器，可以站在上面发动攻击或者甩出去，玩玩游戏就知道了</d>
<d p="1352.3900146484,1,25,16777215,1493710445,0,262e20bc,3301737772">噫，第二季ed啊</d>
<d p="616.25500488281,1,25,16777215,1493711100,0,eb363393,3301762790">这明明是一把锁</d>
<d p="817.13000488281,1,25,16777215,1493711403,0,eb363393,3301774466">两个极右翼互怼</d>
<d p="1127.7800292969,1,25,16777215,1493725654,0,d5d04fb2,3302599704">晓之车</d>
<d p="1311.7800292969,1,25,16777215,1493728693,0,c9212318,3302850380">走好</d>
<d p="329.82598876953,1,25,16777215,1493729803,0,173f56bb,3302943662">都嗑药了，不强对得起制药的人么</d>
<d p="630.79901123047,1,25,16777215,1493732429,0,06fb801a,3303174150">其实她只是果睡</d>
<d p="931.77502441406,1,25,16777215,1493734626,0,4668b5a2,3303379578">那玩意我记得第二部密涅瓦在大气圈里开了三次，全被挡下来了</d>
<d p="1085.5,1,25,16777215,1493734780,0,4668b5a2,3303394054">没有吧</d>
<d p="1328.0999755859,1,25,16777215,1493735023,0,4668b5a2,3303416880">真男人啊</d>
<d p="440.95401000977,1,25,16777215,1493737726,0,742c8bff,3303672040">战斗</d>
<d p="1125.0999755859,1,25,16777215,1493737922,0,742c8bff,3303689962">加了配乐</d>
<d p="1213.6300048828,1,25,16777215,1493738009,0,742c8bff,3303697972">这段很泪目 拂晓那段很泪目</d>
<d p="1245.9300537109,1,25,16777215,1493738041,0,742c8bff,3303700878">其实还有对视哦</d>
<d p="1291.4899902344,1,25,16777215,1493738087,0,742c8bff,3303704982">自由的火种</d>
<d p="1357.9599609375,1,25,16777215,1493738153,0,742c8bff,3303711004">woc！美！</d>
<d p="564.52697753906,1,25,16777215,1493749756,0,3e4e242c,3304294770">不不，要是说了justice也帮着打议长会气死的</d>
<d p="620.57000732422,1,25,16777215,1493749788,0,3e4e242c,3304297340">现在看感觉各种内涵</d>
<d p="1091.6999511719,1,25,16777215,1493751387,0,a2ce77cc,3304322314">致敬</d>
<d p="286.57699584961,1,25,16777215,1493761173,0,3e95df2b,3304416126">才发现2333333</d>
<d p="295.93600463867,1,25,16777215,1493774090,0,a509271d,3304614082">没办法迪亚哥貌似4人组里最没背景的跳反就被降职</d>
<d p="599.69097900391,1,25,16777215,1493787557,0,e2bd51ff,3305339436">其实收集信息主要收集实战数据，机体数据已经有了，就不考虑入去了。</d>
<d p="7.5640001296997,1,25,16777215,1493799273,0,2e9b2253,3306042696">晓之车</d>
<d p="1257.8399658203,1,25,16777215,1493799446,0,2e9b2253,3306049524">牵手成功</d>
<d p="1367.1600341797,1,25,16777215,1493799555,0,2e9b2253,3306054002">这个重置好棒</d>
<d p="365.29699707031,1,25,16777215,1493802139,0,0ac9fb88,3306168266">你打一仗用体力，俺们嗑药打仗用生命啊</d>
<d p="400.57699584961,1,25,16777215,1493802173,0,0ac9fb88,3306169828">神意吧</d>
<d p="536.74499511719,1,25,16777215,1493802309,0,0ac9fb88,3306176126">她自己也不知道自己是新人类，给了拂晓也不开啊</d>
<d p="791.47900390625,1,25,16777215,1493802563,0,0ac9fb88,3306188306">大气层龙骑兵飞不起来用个吊</d>
<d p="907.85601806641,1,25,16777215,1493802681,0,0ac9fb88,3306193824">一般谁没事打加速器啊</d>
<d p="1139.5100097656,1,25,16777215,1493803004,0,0ac9fb88,3306210280">轰开大气层，污染大了</d>
<d p="1334.4799804688,1,25,16777215,1493803199,0,0ac9fb88,3306220452">你不是要加速器么，我炸了它</d>
<d p="1114.5999755859,1,25,16777215,1493823305,0,791ca4e0,3307751408">神曲</d>
<d p="404.73098754883,1,25,16777215,1493827661,0,b604df8a,3308146284">神意近战感觉挺差的啊。。</d>
<d p="1271.1300048828,1,25,16777215,1493828029,0,b604df8a,3308175944">理科的别跑233</d>
<d p="482.54299926758,1,25,16777215,1493831206,0,7b977b78,3308334208">这些愚蠢的地球人</d>
<d p="1096.1199951172,1,25,16777215,1493831938,0,7b977b78,3308357824">什么时候兄妹相认啊</d>
<d p="1096.3699951172,1,25,16777215,1493873111,0,5726e3b8,3309238554">歌是上飞船的时候才开始的</d>
<d p="1258.6999511719,5,25,16707842,1493873847,0,011d6037,3309300870">牵手成功</d>
<d p="1354.9300537109,1,25,16777215,1493887242,0,6706c140,3309918750">拉妖礼服美炸</d>
<d p="1363.3399658203,1,25,16777215,1493887243,0,6706c140,3309919358">卡卡也很美！</d>
<d p="1306.0999755859,1,25,16777215,1493887322,0,6706c140,3309922756">走好</d>
<d p="1375.3399658203,1,25,16777215,1493887463,0,6706c140,3309928182">n周目。。。</d>
<d p="928.95501708984,1,25,16777215,1493894418,0,19758c40,3310313090">那玩意污染很重的，大气层内一般不用，除了某舰长。</d>
<d p="1319.7900390625,1,25,16777215,1493896303,0,19758c40,3310441962">曙光社没炸吧</d>
<d p="251.3990020752,1,25,16777215,1493898135,0,30491320,3310571814">迪亚哥： 我为了妹子战斗</d>
<d p="295.23699951172,1,25,16777215,1493898179,0,30491320,3310575024">套路</d>
<d p="759.65301513672,1,25,16777215,1493898538,0,30491320,3310600810">没有3小强 你们已经OVER了</d>
<d p="1166.2900390625,1,25,16777215,1493898989,0,30491320,3310633354">真男人</d>
<d p="1343.0100097656,1,25,16777215,1493899292,0,30491320,3310655738">真男人</d>
<d p="1004.5200195312,1,25,16777215,1493899465,0,4430381e,3310668438">拂晓在曙光社地下，还没造好呢，开出来送吗？</d>
<d p="739.42102050781,1,25,16777215,1493904939,0,b26b1c2a,3311103068">你自己没电了怪谁</d>
<d p="751.73699951172,1,25,16777215,1493904978,0,b26b1c2a,3311106378">龙骑兵只能在宇宙用</d>
<d p="1003.5300292969,1,25,16777215,1493905258,0,b26b1c2a,3311130166">真是不立flag不舒服，你安静点直接打不行啊</d>
<d p="1048.3100585938,1,25,16777215,1493905346,0,b26b1c2a,3311137772">一架拂晓不只比10架异端强啊，seed还是个特型机无敌的宇宙</d>
<d p="839.73797607422,1,25,16711680,1493910037,0,33e16119,3311560306">余灰追寻火焰2333333333333</d>
<d p="518.29602050781,1,25,16777215,1493910489,0,5e3c6f59,3311605278">卡嘉莉就在今天成长了。。。</d>
<d p="1342.3900146484,1,25,16777215,1493911386,0,5e3c6f59,3311690728">“父亲，再见”</d>
<d p="1345.3800048828,1,25,16777215,1493911458,0,5e3c6f59,3311698258">最后的一声“父亲”真的荡气回肠了。泪目</d>
<d p="146.83599853516,1,25,16777215,1493911734,0,347b2300,3311735746">黎明：我的宇宙？？？</d>
<d p="1159.9200439453,1,25,16777215,1493913677,0,347b2300,3311889314">太太我喜欢你啊</d>
<d p="1271.2800292969,1,25,16777215,1493913922,0,347b2300,3311907172">我们TM射爆</d>
<d p="1365.9499511719,1,25,16777215,1493918504,0,dfb15b20,3312151252">把 地球军目的炸了 不然 地球军这次开始要干坏事 我第一次看感觉是的</d>
<d p="1210.1199951172,1,25,16777215,1493940519,0,ffdf1e15,3312464356">最后的希望啊</d>
<d p="438.25,1,25,16777215,1493966834,0,5d5dbbce,3313628790">神意是传说的前一个版本吧？</d>
<d p="1013.7100219727,1,25,16777215,1493967071,0,5d5dbbce,3313638936">刷拂晓的 拂晓在第二部才出来啊 </d>
<d p="1064.8800048828,1,25,16777215,1493967180,0,5d5dbbce,3313643660">强袭不是核动力 哪能跟上这推进器</d>
<d p="1090.2299804688,1,25,16777215,1493967217,0,5d5dbbce,3313645190">是关门的时候开始的吧？</d>
<d p="1258.7700195312,5,25,16777215,1493971744,0,7a33f2f3,3313850142">恭喜男女嘉宾牵手成功</d>
<d p="1310.6300048828,1,25,16777215,1493977163,0,9d785d11,3314139390">走好，奥布之狮，哈乌梅亚神与你同在</d>
<d p="447.60699462891,1,25,16777215,1493978593,0,b8f91163,3314234262">感觉刚刚穆叔也想来一炮</d>
<d p="6.0781297683716,1,25,16777215,1493997043,0,6317c6cb,3315952206">原來來聽歌的不只有我一個</d>
<d p="79.139999389648,1,25,16777215,1494001463,0,f1cc7063,3316399496">怎么人辣么少？</d>
<d p="366.66000366211,1,25,16777215,1494005038,0,56cb5682,3316613690">清理兵线</d>
<d p="0.25600001215935,1,25,16777215,1494028755,0,1dcac03d,3317073214">神曲</d>
<d p="445.44400024414,1,25,16777215,1494047532,0,d8968e0b,3318233550">说神意近战不行肯定没注意神意的大砍刀</d>
<d p="1078.5,1,25,16777215,1494053478,0,057d9130,3318718664">这里还是看原版好点</d>
<d p="1327.2199707031,1,25,16777215,1494075804,0,6c99c58a,3320708660">真男人</d>
<d p="1201.0100097656,5,25,16777215,1494077699,0,6706c140,3320919862">哈奥米亚神与我们同在！</d>
<d p="1250.7700195312,5,25,16777215,1494077662,0,6706c140,3320926932">玛德空耳你给我出来，看我不打死你哈哈哈哈哈</d>
<d p="1394.0100097656,5,25,16777215,1494077990,0,6706c140,3320950910">为什么没有我kl的特写(´๑•_•๑)</d>
<d p="68.692001342773,1,25,16777215,1494085226,0,45cf4459,3321788826">2017/5/6</d>
<d p="1302.3000488281,1,25,15138834,1494086766,0,dd569099,3321931360">准备暂停截图！</d>
<d p="1343.7299804688,1,25,15138834,1494086757,0,dd569099,3321939416">准备暂停截图！</d>
<d p="1.5520000457764,1,25,16777215,1494133751,0,765066b9,3324400792">陈</d>
<d p="1337.9699707031,1,25,16777215,1494140025,0,4f77d55b,3325041218">土豪金高达即将上线</d>
<d p="1154.0200195312,1,25,13369344,1494140590,0,18137112,3325090824">为片尾拉克丝而来</d>
<d p="60.328998565674,1,25,16777215,1494140772,0,a4b870cc,3325106542">一句台词三个人分的别跑</d>
<d p="253.28999328613,1,25,16777215,1494140867,0,a4b870cc,3325115078">这就是你看海的理由吗</d>
<d p="287.67098999023,1,25,16777215,1494140901,0,a4b870cc,3325118188">这是3A打2S1A啊</d>
<d p="1170.7099609375,1,25,16777215,1494141743,0,a4b870cc,3325190262">卧槽</d>
<d p="1193.9100341797,1,25,16777215,1494141766,0,a4b870cc,3325192188">弟弟还是哥哥不是这俩自己争的吗</d>
<d p="814.25897216797,1,25,16777215,1494151554,0,61561419,3326035398">老版叫蓝波斯菊吧？</d>
<d p="211.82699584961,1,25,16777215,1494157693,0,15b9b958,3326576052">讲个笑话 动漫讲科学</d>
<d p="1205.4599609375,1,25,16777215,1494170083,0,e137ed11,3327756344">听了晓之车十年后第一次看seed，感动得一塌糊涂</d>
<d p="830.77697753906,1,25,16777215,1494171300,0,7ae5ca22,3327867144">传火吧大天使号</d>
<d p="1261.8900146484,1,25,16777215,1494173892,0,cf82d152,3328070600">牵手成功</d>
<d p="192.29200744629,1,25,16777215,1494217961,0,6aed70f7,3329130938">应该叫胡子密</d>
<d p="1378.25,1,25,16777215,1494228153,0,5d395808,3329671052">5个红衣，正好是夺取5台地球军机，拉斯提半当中死了。。</d>
<d p="931.3740234375,1,25,16777215,1494251201,0,c262e236,3331113126">第一是污染第二好像是散热问题地球没宇宙散热好</d>
<d p="541.16400146484,1,25,16777215,1494253538,0,1f77d5dc,3331329002">这么剩钱的翻译？</d>
<d p="1315.6999511719,1,25,16777215,1494298100,0,f9f3ed98,3332586692">卧槽 又自爆</d>
<d p="342.93099975586,5,25,41194,1494298794,0,5a4f6d08,3332607174">MS为什么要站桩输出啊</d>
<d p="1024.2900390625,1,25,16777215,1494301913,0,6470b28f,3332707780">就是不允许也要发射</d>
<d p="1079.5699462891,1,25,16777215,1494301979,0,6470b28f,3332710012">这个好像是大阪腔</d>
<d p="1119.7600097656,1,25,16777215,1494302025,0,6470b28f,3332711714">这个还是新版</d>
<d p="1178.8199462891,1,25,16777215,1494302079,0,6470b28f,3332714248">真失散多年</d>
<d p="1347.3299560547,1,25,16777215,1494302178,0,6470b28f,3332721854">舰长席</d>
<d p="543,1,25,16777215,1494309706,0,b2ee88b2,3333153944">字幕组不走心呀，这样可不对哟？</d>
<d p="612,1,25,16777215,1494309774,0,b2ee88b2,3333156696">被睡了。。。？</d>
<d p="275.30200195312,1,25,16777215,1494312592,0,c4c883ad,3333255958">然而OC时代C也能肛你S← ←</d>
<d p="680.33801269531,5,25,13369395,1494313512,0,c4c883ad,3333286400">↓少女の剑技↓</d>
<d p="1250.9499511719,5,25,16777215,1494315556,0,c4c883ad,3333357614">因为不是红角啊233</d>
<d p="1314.5799560547,5,25,16777215,1494315924,0,c4c883ad,3333370852">↓秋名山车神又出现了！↓</d>
<d p="1341.8100585938,5,25,16777215,1494316595,0,c4c883ad,3333395284">胡子密：老子的东西就算炸了也不便宜你们这群扑街</d>
<d p="1248.4899902344,1,25,38979,1494323008,0,34e69d7d,3333662462">卡在一个奇怪的地方</d>
<d p="146.97200012207,1,25,16777215,1494323547,0,c49dc9dc,3333690528">+1</d>
<d p="280.76000976562,1,25,16777215,1494324107,0,a52475bf,3333720658">才发现</d>
<d p="635.89697265625,1,25,16777215,1494324462,0,a52475bf,3333741062">瞬间黄了</d>
<d p="1348.1600341797,1,25,16777215,1494325174,0,a52475bf,3333782434">果断</d>
<d p="366.59100341797,1,25,16777215,1494327707,0,6c696fe6,3333941526">835的暴露时间了</d>
<d p="214.47700500488,1,25,16777215,1494332517,0,7b745c8d,3334263476">卡嘉莉有资格做总指挥吗？</d>
<d p="1101.4399414062,1,25,16777215,1494333404,0,7b745c8d,3334327046">领导都没有走，反而在操作电脑。有骨气</d>
<d p="1233.2199707031,1,25,16777215,1494333536,0,7b745c8d,3334336674">卡嘉莉和基拉本来就没有达到过爱层面的感情</d>
<d p="1340.5400390625,1,25,16777215,1494333643,0,7b745c8d,3334344666">这里确实没有以前TV版感动。音乐起来的有点晚</d>
<d p="871.65997314453,1,25,16777215,1494345726,0,36eb8f7c,3335327210">不不不不。。。这火我不传。。</d>
<d p="1209.8100585938,1,25,16777215,1494346064,0,36eb8f7c,3335349540">奥布之魂不会灭</d>
<d p="1330.0400390625,1,25,16777215,1494346184,0,36eb8f7c,3335357122">奥布之狮，真男人。。走好。。。</d>
<d p="304.61199951172,1,25,16777215,1494349493,0,2a780c29,3335542458">强行达成共识（睡服）</d>
<d p="1158.0899658203,1,25,16777215,1494350851,0,8bad3b58,3335592464">有情人终成姐弟。。。。</d>
<d p="163.94599914551,1,25,16777215,1494396976,0,dcc0d13c,3336760532">真●嘴炮</d>
<d p="384.21899414062,1,25,16777215,1494397260,0,dcc0d13c,3336771466">自由算是中距离</d>
<d p="446.85299682617,1,25,16777215,1494397346,0,dcc0d13c,3336774620">背包累赘？</d>
<d p="454.44799804688,1,25,16777215,1494397367,0,dcc0d13c,3336775428">最后全靠背包</d>
<d p="1191.2900390625,1,25,16777215,1494398143,0,dcc0d13c,3336803924">炸城了</d>
<d p="1100.0899658203,1,25,16777215,1494411064,0,4e2cf2c1,3337387030">第二季只想给福田寄刀片</d>
<d p="1297.6800537109,1,25,16777215,1494411282,0,4e2cf2c1,3337400452">太悲壮了 这一幕塑造的太成功了</d>
<d p="343.0539855957,1,25,16777215,1494415017,0,75ed48e0,3337660068">忘了爆种吗</d>
<d p="153.57200622559,5,25,16707842,1494420496,0,d74de401,3338059938">这个嘴，我有个大胆的想法(●—●)</d>
<d p="329.08801269531,1,25,16777215,1494440895,0,5ea00abf,3339369674">在奥布用洋电子就不怕被污染？</d>
<d p="410.60699462891,1,25,16777215,1494440920,0,5ea00abf,3339371902">你要知道神逾在地球还不如一台村雨，</d>
<d p="581.18798828125,1,25,16777215,1494441162,0,5ea00abf,3339376060">三小强杀手，连自由与正义也打不下三小强</d>
<d p="1047.9699707031,1,25,16777215,1494441755,0,5ea00abf,3339384182">主要是暴风不会飞，第一季会飞的很少</d>
<d p="1023.5399780273,1,25,16777215,1494498997,0,0174124f,3341179748">修是谁？</d>
<d p="1269.4899902344,1,25,16777215,1494500314,0,1a305948,3341263704">这枪法</d>
<d p="1363.8100585938,1,25,16777215,1494500525,0,e789068c,3341277252">阿斯兰这身衣服有点浪漫</d>
<d p="1175.2299804688,1,25,16777215,1494507273,0,7df3edff,3341748486">爆炸</d>
<d p="913.51898193359,1,25,16777215,1494517571,0,c0630b52,3342649610">本来就想拿到加速器的啊 怎么可能打</d>
<d p="1.0240000486374,1,25,16777215,1494517579,0,a682e333,3342650194">逝者安息</d>
<d p="551.73400878906,1,25,16777215,1494580292,0,69de9eb7,3344882020">自动屏蔽了你们家两台机</d>
<d p="1314.8000488281,1,25,16777215,1494581071,0,69de9eb7,3344930616">敬礼</d>
<d p="365.98599243164,1,25,16777215,1494598145,0,66884e35,3346390764">前面骁龙的你过来，我给你加个buff</d>
<d p="271.51901245117,5,25,16777215,1494599883,0,e110cc47,3346568530">不小心踩到   剧终</d>
<d p="855.47900390625,1,25,16777215,1494601124,0,e110cc47,3346695520">基拉内心：看过来了！！赶紧卖一波萌</d>
<d p="651.48999023438,1,25,16777215,1494601748,0,52b975cd,3346757768">爆种虐3小强</d>
<d p="158.06199645996,5,25,15138834,1494602309,0,6ddaec35,3346812930">菊花嘴</d>
<d p="188.10200500488,5,25,15138834,1494602335,0,6ddaec35,3346816988">认真你就输了</d>
<d p="1350.7800292969,5,25,15138834,1494603516,0,6ddaec35,3346927528">泪目</d>
<d p="600.74499511719,5,25,16777215,1494606249,0,92c9d771,3347155102">↓事后</d>
<d p="1311.9699707031,5,25,16777215,1494606931,0,92c9d771,3347203298">汉子，走好</d>
<d p="1165.2199707031,1,25,16777215,1494619186,0,42aa8232,3347616210">有情人终成姐弟</d>
<d p="388.76000976562,1,25,16777215,1494646710,0,f1b9453d,3348546872">现在的自由有没有浮游炮？忘了</d>
<d p="455.88000488281,1,25,16777215,1494646903,0,f1b9453d,3348553008">背包是推进器</d>
<d p="307.86401367188,1,18,16777215,1494648040,0,808cb4e5,3348635126">真的一个画面用两季</d>
<d p="354.22500610352,1,25,16777215,1494648113,0,808cb4e5,3348639444">直接开大啊</d>
<d p="402.3630065918,1,25,16777215,1494648178,0,808cb4e5,3348644064">下一季的强袭自由才有浮游炮</d>
<d p="453.24301147461,1,25,16777215,1494648256,0,808cb4e5,3348649616">迪亚的画面好省钱啊</d>
<d p="1256.1400146484,1,25,16777215,1494650701,0,6ef74b39,3348848326">原版这里太搞笑.明明不停落后中..却突然可以牵住了</d>
<d p="1365.4899902344,1,25,16777215,1494650853,0,6ef74b39,3348863046">重制版才有这个</d>
<d p="1381.3199462891,1,25,16777215,1494650909,0,6ef74b39,3348868096">哪时海涅..第二季..阿斯兰根本不认识他</d>
<d p="337.19000244141,1,25,16777215,1494651872,0,d948813f,3348958134">那是主炮啊，都没用主炮，污染个鸡毛啊</d>
<d p="455.56399536133,1,25,16777215,1494652034,0,d948813f,3348971390">你口中的累赘猛得不行</d>
<d p="1189.2199707031,1,25,16777215,1494652043,0,0225b5f4,3348972166">好人活不长系列</d>
<d p="1175.9300537109,1,25,16777215,1494652831,0,d948813f,3349040810">说了多少次，是弟弟，不看清楚的吗？</d>
<d p="612.61499023438,1,25,16777215,1494661632,0,48741285,3349732682">油玩儿睡服</d>
<d p="1299.5699462891,1,25,16777215,1494662337,0,48741285,3349784192">一路走好</d>
<d p="1318.9300537109,1,25,16777215,1494662364,0,48741285,3349787152">起立敬礼</d>
<d p="1341.8900146484,1,25,16777215,1494662398,0,48741285,3349789640">这批才是真领导</d>
<d p="1345.5300292969,1,25,16777215,1494662415,0,48741285,3349790834">第二季的简直就是混蛋</d>
<d p="1380.3699951172,1,25,16777215,1494662465,0,48741285,3349794436">暂停看拉丝提</d>
<d p="1387.7299804688,1,25,16777215,1494662375,0,48741285,3349795722">终于看见拉丝提脸了</d>
<d p="84.762001037598,1,25,16777215,1494672331,0,d5fd2b7a,3350584516">20170513</d>
<d p="1307.6600341797,1,25,16777215,1494673552,0,d5fd2b7a,3350692834">泪目</d>
<d p="747.80902099609,1,25,16777215,1494690141,0,9d586a86,3352311062">下巴都是红的</d>
<d p="1318.9100341797,1,25,15138834,1494691861,0,b26aa56d,3352475934">你萌是英雄</d>
<d p="1300.7900390625,1,25,15138834,1494692833,0,e1f006a8,3352564502">你TM不是要质量加速器吗，老子就炸了它</d>
<d p="1263.5200195312,1,25,16777215,1494721141,0,45f4629d,3353523280">半血无限飞了吧</d>
<d p="412.25,1,25,16777215,1494723128,0,993e59bf,3353612714">神意第一季顶点机</d>
<d p="560.88299560547,1,25,16777215,1494736374,0,c6f40a9d,3354686716">自由和正义是最高机密，他们也不知道数据的</d>
<d p="1320.7299804688,1,25,16777215,1494737118,0,c6f40a9d,3354760624">奥布还有秘密基地，炸掉的也只是地面上的</d>
<d p="1110.3499755859,1,25,16777215,1494746847,0,49e1bacd,3355733676">帝国的毁灭！</d>
<d p="959.78802490234,1,25,6749952,1494756891,0,5dc7f199,3356594808">看我颜色</d>
<d p="1034.3000488281,1,25,16777215,1494758068,0,0459a5e6,3356690532">黄金MS 佛晓</d>
<d p="2.9260199069977,1,25,16777215,1494762107,0,e804a585,3357029742">听晓の车的别走！承包就为了晓の车 带我一起走</d>
<d p="191.61799621582,1,25,16777215,1494762247,0,75b19cc8,3357041268">胡子密SAMA</d>
<d p="1116.3100585938,1,25,16777215,1494763162,0,e804a585,3357117780">QAQ晓の车 每次都想泪目</d>
<d p="1204.0500488281,5,25,16776960,1494763279,0,e804a585,3357127434">哈奥米亚神与我们同在！</d>
<d p="344.59399414062,1,25,16777215,1494768871,0,384e3680,3357637544">不是每个人都是基神</d>
<d p="442.19900512695,1,25,16777215,1494769030,0,384e3680,3357652404">回旋刀有喷射孔的</d>
<d p="677.75701904297,5,25,16777011,1494769371,0,384e3680,3357683692">↓↓坐上去自己动了</d>
<d p="842.29901123047,1,25,16777215,1494771085,0,50b238f4,3357848386">不传，滚</d>
<d p="1389.1099853516,1,25,16777215,1494777717,0,09840c51,3358469610">为啥基拉的衣服老是那么非主流呢</d>
<d p="378.08200073242,1,25,16777215,1494822466,0,a4964a06,3359560236">清理屏幕</d>
<d p="613.24597167969,1,25,38979,1494826156,0,366ee2a9,3359822110">克队:小伊，你要学会原谅</d>
<d p="715.38598632812,1,25,38979,1494826281,0,366ee2a9,3359829688">夏尼还算是有点真本事的，近距离都不虚基神</d>
<d p="1271.0999755859,1,25,38979,1494826529,0,366ee2a9,3359844066">要是枪法好怎么会当三小强</d>
<d p="1308.4200439453,5,25,16777215,1494850661,0,0767d936,3361136586">敬你是条汉子</d>
<d p="159.61599731445,1,25,16777215,1494861595,0,9e010b69,3362062366">那个又想法的别走23333</d>
<d p="292.32998657227,1,25,16777215,1494865288,0,44021249,3362350300">迪亚加作为没背景的红衣叛变当然降级</d>
<d p="1311.7700195312,1,25,16777215,1494866066,0,44021249,3362393766">奥布之狮走好</d>
<d p="486.875,1,25,15138834,1494890545,0,0889fcce,3362796126">啊！把迷途也打爆了。。。</d>
<d p="930.32202148438,1,25,15138834,1494891085,0,0889fcce,3362802556">阳电子炮在地球环境中冷却要很久</d>
<d p="1003.6199951172,5,25,15138834,1494891252,0,0889fcce,3362804846">flag 立！   bgm 起！   一起骂～死!</d>
<d p="1252.0899658203,5,25,15138834,1494891673,0,0889fcce,3362810092">尔康手</d>
<d p="1275.8100585938,5,25,15138834,1494891730,0,0889fcce,3362810786">奥义！真·合体光线</d>
<d p="1105.7299804688,1,25,16777215,1494912131,0,060624e4,3363490442">原来300的那句语音来自这集啊</d>
<d p="1317.1099853516,1,25,16777215,1494940059,0,fe2f78a2,3365048364">走好</d>
<d p="1354.9699707031,1,25,16777215,1494940089,0,fe2f78a2,3365051884">拉克丝？？？</d>
<d p="382.0539855957,1,25,16777215,1494943224,0,28a38809,3365314598">核動力就是好</d>
<d p="1300.4499511719,5,25,16777215,1494954099,0,6c0165ca,3366134826">走好!</d>
<d p="1300.5300292969,5,25,16777215,1494954125,0,6c0165ca,3366135850">走好!</d>
<d p="1300.3499755859,5,25,16777215,1494954143,0,6c0165ca,3366136622">走好!</d>
<d p="337,1,25,16777215,1494975399,0,5e2cb4ec,3366454320">正电子炮这种反物质武器还是不能在地球随便用的</d>
<d p="982.28997802734,1,25,14811775,1494977372,0,9fab1c3f,3366478804">开弹幕了？</d>
<d p="1328.1500244141,1,25,15138834,1494983727,0,9bce8524,3366599634">奥布不会任你们摆布。</d>
<d p="194.77699279785,5,25,16777215,1494999552,0,0d56ee16,3367284364">一瞬间EVA既视感</d>
<d p="317.42098999023,1,25,14811775,1495021896,0,8073b4c2,3368439534">1.地球上有空气，而太空环境是接近真空的。</d>
<d p="318.23001098633,5,25,14811775,1495022132,0,8073b4c2,3368455958">1.在地球上有空气，而太空是接近真空环境</d>
<d p="318.23001098633,5,25,14811775,1495022271,0,8073b4c2,3368465708">2.阳电子破城炮本质是一种反物质武器</d>
<d p="318.23001098633,5,25,14811775,1495022333,0,8073b4c2,3368470150">3.反物质武器通过正反物质相碰泯灭产生能量来破坏结构</d>
<d p="318.23001098633,5,25,14811775,1495022392,0,8073b4c2,3368475416">4.空气是最常见的正物质，会于阳电子相互泯灭</d>
<d p="318.23001098633,5,25,14811775,1495022562,0,8073b4c2,3368487238">6.地球发射破城炮，会因为与空气泯灭而使威力极速衰减</d>
<d p="318.23001098633,5,25,14811775,1495022629,0,8073b4c2,3368490950">7.此外还会产生很多副效果，如这集最后的加速效果</d>
<d p="439.81201171875,5,25,16777215,1495028771,0,cccf1a6e,3368967280">地球军，新人类的叛徒们</d>
<d p="530.94799804688,5,25,16777215,1495028883,0,cccf1a6e,3368975422">不对，我就服了</d>
<d p="1268.7299804688,5,25,16777215,1495029199,0,cccf1a6e,3369002346">啥准头</d>
<d p="325.72100830078,1,25,16777215,1495030157,0,c51cafd1,3369084104">战舰一死死一堆</d>
<d p="414.98001098633,1,25,16777215,1495030246,0,c51cafd1,3369091740">天意只能在宇宙玩 来不了大气层</d>
<d p="497.87399291992,1,25,16777215,1495030331,0,c51cafd1,3369099168">简直浆糊装甲</d>
<d p="533.94097900391,1,25,16777215,1495030365,0,c51cafd1,3369102200">奥布意志</d>
<d p="703.93902587891,1,25,16777215,1495030490,0,c51cafd1,3369113042">强骑</d>
<d p="1192.7600097656,1,25,16777215,1495030634,0,c51cafd1,3369125698">是卡嘉莉认为的弟弟</d>
<d p="1238.6300048828,1,25,16777215,1495030680,0,c51cafd1,3369129606">牵手失败怎么办</d>
<d p="1309.2199707031,1,25,16777215,1495030750,0,c51cafd1,3369135652">奥布的意志</d>
<d p="1412.9200439453,1,25,16777215,1495030854,0,c51cafd1,3369144548">经历过第一次大战的红衣和后面红衣 实力不一样的</d>
<d p="618.30102539062,1,25,16777215,1495039003,0,fd655085,3369773770">卡密</d>
<d p="1047.7800292969,1,25,16777215,1495039119,0,ada42471,3369779800">跳过37就为了晓之车</d>
<d p="1194.4899902344,1,25,16777215,1495039239,0,ada42471,3369785924">原版是不是有歌词字幕</d>
<d p="1253.6099853516,1,25,16777215,1495039298,0,ada42471,3369788944">下了命令不能打质量加速器</d>
<d p="973.73901367188,1,25,16777215,1495039382,0,fd655085,3369792878">当然是选择原谅她啊</d>
<d p="1163.8599853516,1,25,16777215,1495039571,0,fd655085,3369802330">基拉</d>
<d p="398.95599365234,1,25,16777215,1495040831,0,ae859491,3369859602">强袭自由才有浮游炮</d>
<d p="967.82897949219,1,25,16777215,1495041151,0,c12c18be,3369871588">当然是原谅她</d>
<d p="406.22799682617,1,25,16777215,1495050214,0,2345b281,3370057134">强袭自由是龙骑兵不是浮游炮</d>
<d p="1123.4499511719,5,18,13382502,1495083255,0,d977e877,3370540741">俯卧在随风起舞的树荫下哭泣着</d>
<d p="1127.4499511719,5,18,16711833,1495083292,0,d977e877,3370543455">望着那个素不相识的自己</d>
<d p="1132.4899902344,5,18,16711833,1495083342,0,d977e877,3370547157">吉他为失去的人而弹奏</d>
<d p="1142.6899414062,5,18,16711833,1495083388,0,d977e877,3370550365">流星因不归之人而陨落</d>
<d p="1150.8399658203,5,18,16711833,1495083496,0,d977e877,3370557859">不要离我而去</d>
<d p="1150.8399658203,5,18,16711833,1495083521,0,d977e877,3370559473">即使是这样恳求  　　也只是换来橙色花瓣的静静摇曳，</d>
<d p="1150.8399658203,5,18,16711833,1495083575,0,d977e877,3370563383">遗留在稚嫩脸庞上的手掌中的记忆 ，已渐远去。</d>
<d p="1164.5100097656,5,18,16711833,1495083615,0,d977e877,3370566187">指尖弹奏出别离的旋律 ，依靠在你温柔翅膀上那稚嫩的心</d>
<d p="1169.5400390625,5,18,16711833,1495083693,0,d977e877,3370571611">被呼啸的车轮无情的抛开，吉他弹奏出逝人的叹息</d>
<d p="485.79501342773,1,25,16777215,1495086050,0,3458c10d,3370715389">应该能吧</d>
<d p="1165.9699707031,5,18,16724889,1495092477,0,d977e877,3370966507">拨弄着心弦无法平静</d>
<d p="1173.7600097656,5,18,16724889,1495092521,0,d977e877,3370968007">在未被悲伤沾染的洁白上映出了摇曳着橙色花瓣的夏日之影</d>
<d p="1351.4499511719,5,18,16724889,1495092697,0,d977e877,3370974183">目送拂晓的列车 ~~</d>
<d p="74.921997070312,1,25,16777215,1495099449,0,6d0de40c,3371245259">0516</d>
<d p="1307.5799560547,1,25,16777215,1495104849,0,30491320,3371569609">奥布有一点强</d>
<d p="384.73599243164,1,25,16777215,1495120750,0,dca3b708,3372786999">这个背景音乐GOOD</d>
<d p="699.84399414062,1,25,16777215,1495128153,0,9da8b0f6,3373222845">骑上来23333333</d>
<d p="472.04501342773,1,25,16777215,1495168345,0,b5c55cf2,3374140145">盾牌好像没卵用啊</d>
<d p="588.27301025391,1,25,16777215,1495178411,0,617092d2,3374781175">相良</d>
<d p="1252.4399414062,1,25,16777215,1495182378,0,3eebe24d,3374969837">好像美队和冬兵的故事...</d>
<d p="1303.4100341797,1,25,16777215,1495189433,0,30491320,3375435415">这批领导人真心刚</d>
<d p="1181.8800048828,1,25,16777215,1495190328,0,70891448,3375540169">你爆个种 她爸就不会死了</d>
<d p="88.850997924805,1,25,16777215,1495199502,0,250c614f,3376309969">20170519</d>
<d p="87.459999084473,1,25,16777215,1495206010,0,511bdf72,3376951179">20170519</d>
<d p="1382.8100585938,1,25,16777215,1495213133,0,0f1237df,3377527627">不是看过以为完结撒花了</d>
<d p="1399.4799804688,1,25,16777215,1495213156,0,0f1237df,3377528885">完结撒花</d>
<d p="188.85000610352,5,25,16777215,1495213783,0,355c9d69,3377564173">认真你就输了</d>
<d p="218.27099609375,1,25,16777215,1495213876,0,355c9d69,3377569247">卡嘉莉指挥能力还是可以的</d>
<d p="252.68200683594,1,25,16777215,1495213937,0,355c9d69,3377573251">阿斯兰：就算是为了基拉，我也。。。。</d>
<d p="284.95901489258,1,25,16777215,1495213996,0,355c9d69,3377576451">迪亚加你的立场很微妙啊</d>
<d p="296.4049987793,1,25,16777215,1495214069,0,355c9d69,3377579417">似乎达成了叛变的共识.jpg</d>
<d p="336.25,1,25,16777215,1495214130,0,355c9d69,3377582687">三小强表现已经很出色了</d>
<d p="399.20999145508,1,25,16777215,1495214259,0,355c9d69,3377589311">能把基神逼到这种程度，三小强真的不错了</d>
<d p="250.90100097656,1,25,41194,1495257393,0,f8685da8,3379253483">棺材店老板忙的，五金店老板更忙</d>
<d p="279.64001464844,1,25,16777215,1495260880,0,092c6168,3379538391">你TM才发现我</d>
<d p="266.17401123047,1,25,16777215,1495265700,0,ecc158a2,3379890237">我充值人民币承包了(. ❛ ᴗ ❛.)因为这部是我最喜欢的动漫没有之一。</d>
<d p="559.93902587891,1,25,16777215,1495266033,0,ecc158a2,3379914223">最初的版本，乌兹米尤拉阿斯哈  阿斯兰萨拉 买的官版杂志也是</d>
<d p="420.50399780273,1,25,16777215,1495279395,0,002fe7e1,3381030949">神意是最早用龙骑兵的机体吧</d>
<d p="751.83099365234,1,25,16777215,1495283537,0,e7aae2d1,3381415471">IWSP</d>
<d p="60.67200088501,1,25,16777215,1495283727,0,b224886a,3381433199">20170520</d>
<d p="1249.1199951172,1,25,16777215,1495283901,0,c9b914ce,3381459725">这个红色有角的居然不是三倍速。。。。</d>
<d p="859.07000732422,1,25,16777215,1495291424,0,807e72c6,3382207739">完全看不出来奥布要输了</d>
<d p="845.09002685547,1,25,16777215,1495302789,0,80d3a06e,3383256761">星星之火，可以燎原</d>
<d p="485.14700317383,1,25,16777215,1495316991,0,101ea483,3383569679">对的是你们要完了</d>
<d p="82.122001647949,1,25,16777215,1495333482,0,7133bc01,3384278937">2017  5    21</d>
<d p="213,1,25,16777215,1495361022,0,eed39031,3386844619">趁牛顿没反应过来，赶紧</d>
<d p="1174.0100097656,1,25,16777215,1495363147,0,17ba2635,3387155631">难怪要换妻</d>
<d p="608.00598144531,1,25,16777215,1495375693,0,d5c7a42f,3388341501">到底是不是被睡了？？</d>
<d p="121.9879989624,1,25,16777215,1495376044,0,6ba21f69,3388377139">少女时的拉克丝</d>
<d p="1041.25,5,25,16777215,1495386985,0,4836c5e6,3389280001">草薙(ti)号</d>
<d p="1216.5100097656,1,25,6750054,1495440979,0,d977e877,3390872923">依靠在你温柔翅膀上那稚嫩的心</d>
<d p="1127.3399658203,1,25,16777215,1495441099,0,d977e877,3390877357">超喜欢的晓之车！！1</d>
<d p="1199.6300048828,1,25,16777215,1495441192,0,d977e877,3390881241">哈奥米亚神与我们同在！</d>
<d p="998.91998291016,1,25,16777215,1495443430,0,2061376b,3390979475">睡服他</d>
<d p="1112.9200439453,1,25,16777215,1495443544,0,2061376b,3390984499">这里她爸是觉得找到了希望，所以自己一定要保住火种</d>
<d p="641.38299560547,5,25,16776960,1495446791,0,bcfad84c,3391161221">前方膜法预警</d>
<d p="1104.2099609375,1,25,16777215,1495456241,0,bcfad84c,3392250871">来吧？？</d>
<d p="381.47900390625,1,25,16777215,1495461526,0,5e61a5c8,3392679093">看把基神能的</d>
<d p="1134.4100341797,1,25,16777215,1495462279,0,5e61a5c8,3392744163">神曲</d>
<d p="1277.0699462891,1,25,16777215,1495462421,0,5e61a5c8,3392756919">轰</d>
<d p="1315.8800048828,1,25,16777215,1495462460,0,5e61a5c8,3392760547">一言不合就自爆</d>
<d p="734.29498291016,1,25,16777215,1495467031,0,30491320,3393172551">切 没有三小强 你们早被开无双了</d>
<d p="2.3800001144409,1,25,16777215,1495483909,0,666ddce5,3393787985">三赖子</d>
<d p="249.8509979248,1,25,16777215,1495484083,0,666ddce5,3393789401">又来这段</d>
<d p="350.09100341797,1,25,16777215,1495484100,0,666ddce5,3393790579">自由人操作不好</d>
<d p="1055.4300537109,1,25,16777215,1495485049,0,666ddce5,3393797219">暴风是炮台机动性不好</d>
<d p="1312.3800048828,1,25,16777215,1495485343,0,666ddce5,3393799419">我敬你是条汉子</d>
<d p="680.15197753906,5,25,16777215,1495538974,0,970242d8,3395801277">双燕斩</d>
<d p="1223.5899658203,1,25,16777215,1495539346,0,9b2d53fd,3395829197">这就是战争</d>
<d p="1230.6700439453,1,25,16777215,1495539371,0,9b2d53fd,3395831015">这就是战争</d>
<d p="122.11199951172,1,25,16777215,1495560150,0,806e51e3,3397429519">20160524</d>
<d p="1115.2299804688,1,25,16777215,1495572800,0,0abf7ad2,3397646107">神曲 起~~卡写索索~</d>
<d p="1331.5,1,25,16777215,1495573017,0,0abf7ad2,3397647859">全体起立</d>
<d p="398.66101074219,1,25,16777215,1495587083,0,335f3212,3397823817">强袭自由才有ai炮</d>
<d p="284.41900634766,1,25,16777215,1495596036,0,5e61a5c8,3398078107">迪亚哥：你才看到我吗</d>
<d p="750.22497558594,1,25,16777215,1495596502,0,5e61a5c8,3398094605">因为你们选错对战目标了</d>
<d p="1025.3699951172,1,25,16777215,1495596777,0,5e61a5c8,3398104171">上宇宙了，快跑吧，不然削棍狂魔要开挂了</d>
<d p="1023.8200073242,1,25,16777215,1495621556,0,94462574,3399376617">穆叔的</d>
<d p="1273.8499755859,1,25,16777215,1495621934,0,94462574,3399395097">开大了</d>
<d p="304.43399047852,1,25,16777215,1495622197,0,6754c80b,3399413855">都是因为爱</d>
<d p="648.75299072266,1,25,16777215,1495636800,0,840e9ce4,3400605783">-1s</d>
<d p="907.71301269531,1,25,16777215,1495637067,0,840e9ce4,3400631071">这肌肉，，，</d>
<d p="822.458984375,1,25,16777215,1495695928,0,f2ef88f5,3402656639">左倾才是冒险主义，这俩都是左翼，右翼早TM和好了</d>
<d p="1096.3699951172,1,25,16777215,1495704000,0,d6743194,3402968200">神曲即将上线，非战斗人员迅速撤离</d>
<d p="989.81896972656,1,25,16777215,1495704774,0,dae9d37a,3403006252">就这样被拐了</d>
<d p="679.70599365234,1,25,16777215,1495712756,0,9c59bd43,3403522824">厉害了</d>
<d p="776.69897460938,1,25,16777215,1495712857,0,9c59bd43,3403529708">胡子大叔</d>
<d p="902.99200439453,1,25,16777215,1495712993,0,9c59bd43,3403539102">为啥都是妹子</d>
<d p="1129.5300292969,1,25,16777215,1495713225,0,9c59bd43,3403555018">来了来了！</d>
<d p="1278.3699951172,1,25,16777215,1495713457,0,9c59bd43,3403571966">合体</d>
<d p="1319.6700439453,1,25,16777215,1495713521,0,9c59bd43,3403575260">走好</d>
<d p="70.615997314453,1,25,16777215,1495730087,0,f020d332,3404953298">20170526</d>
<d p="113.49600219727,1,25,16777215,1495730267,0,f020d332,3404956696">有人吗？</d>
<d p="120.06400299072,1,25,16777215,1495782801,0,8189b4d6,3406645860">'</d>
<d p="449.33499145508,1,25,16777215,1495791274,0,b63411f8,3406999956">迪亚哥守高地  鸡狼外面输出啊2333333</d>
<d p="150.06700134277,1,25,16777215,1495808388,0,057c3788,3407640142">+999</d>
<d p="174.83999633789,1,25,16777215,1495808413,0,057c3788,3407641237">.</d>
<d p="1176.2600097656,1,25,16777215,1495810576,0,e82e7cb3,3407738338">扎心了老爸</d>
<d p="1338.2700195312,1,25,16777215,1495821295,0,ba1dfdf7,3408068076">敬礼</d>
<d p="605.55700683594,1,25,16777215,1495843357,0,e8a2660a,3408212319">事后？</d>
<d p="1336.1899414062,1,25,16777215,1495878256,0,db196979,3409061938">向奥布之狮致敬！</d>
<d p="13.019000053406,1,25,16777215,1495884661,0,9b765f28,3409308842">恩 是的 和胖虎 小胡一起</d>
<d p="417.23699951172,1,25,16777215,1495956461,0,a2b21fd4,3411649600">强袭除了浮游炮还有流星</d>
<d p="1380.4899902344,1,25,16777215,1495957289,0,a2b21fd4,3411683462">教主</d>
<d p="91.921997070312,1,25,16711833,1495962927,0,8863c83c,3411916225">2017年5月28日 17:14:44</d>
<d p="190.81100463867,1,25,16711833,1495971843,0,8863c83c,3412338098">科学是啥？</d>
<d p="466.00698852539,1,25,16711833,1495972238,0,8863c83c,3412357274">所以说妹子是作用的很大的，穆叔基神亚哥统统是被长腿的妹子收服</d>
<d p="1343.4499511719,1,25,16777215,1495973755,0,6bf9c485,3412432706">向奥布之狮致敬</d>
<d p="1335.8299560547,1,25,16711833,1495973994,0,8863c83c,3412443599">这是三星的仓库吧？</d>
<d p="166.25199890137,1,25,16777215,1495982990,0,b7d86577,3412942613">澳大利亚？</d>
<d p="189.8509979248,1,25,16777215,1495983039,0,b7d86577,3412945554">要科学，看科学类视频去</d>
<d p="201.0119934082,1,25,16777215,1495983065,0,b7d86577,3412947069">理论的话其实可以看百度百科去</d>
<d p="1033.0300292969,1,25,16777215,1495988745,0,b2cdd87f,3413251166">原版的从这个镜头开始放晓之车的BGM了</d>
<d p="1104.5999755859,1,25,16777215,1495989255,0,b2cdd87f,3413272896">重置版的BGM没有原版的放的时机好！</d>
<d p="645.29498291016,1,25,16777215,1496008293,0,05a24e24,3413574257">蛤？？？</d>
<d p="1308.8199462891,1,25,16777215,1496024734,0,c1e0235e,3413957537">奥布之魂！走好！</d>
<d p="547.48699951172,1,25,16777215,1496028286,0,5e61a5c8,3414107359">水下观察</d>
<d p="594.13299560547,1,25,16777215,1496028332,0,5e61a5c8,3414109457">红衣就剩他一个没反水了，省着点用</d>
<d p="999.09399414062,1,25,16777215,1496028737,0,5e61a5c8,3414128203">基神这对大眼睛啊</d>
<d p="1210.9799804688,1,25,16777215,1496028959,0,5e61a5c8,3414138117">三小强：还有一个，赶紧打下来1</d>
<d p="1277.8199462891,1,25,16777215,1496029028,0,5e61a5c8,3414141526">轰啊</d>
<d p="863.70001220703,1,25,16777215,1496032927,0,6355850c,3414334776">兄弟们，奥布什么都不缺，就缺人啊</d>
<d p="863.70001220703,5,25,16777215,1496032934,0,6355850c,3414335170">兄弟们，奥布什么都不缺，就缺人啊</d>
<d p="842.45300292969,1,25,16777215,1496034276,0,8d4a5735,3414409481">都不爆种</d>
<d p="951.77301025391,1,25,16777215,1496034388,0,8d4a5735,3414415536">诶</d>
<d p="393.60400390625,1,25,16777215,1496039163,0,d2d549b9,3414661833">浮游炮是在宇宙用的</d>
<d p="877.81896972656,1,25,16777215,1496039209,0,42e8654f,3414664178">父亲：你们别动我女儿啊</d>
<d p="606.23901367188,1,25,16777215,1496053323,0,bb448d6f,3415368767">裸睡？？？</d>
<d p="1120.7199707031,1,25,16707842,1496064163,0,21b7cdb0,3415965561">旋律开始</d>
<d p="1397.2800292969,1,25,16707842,1496064339,0,21b7cdb0,3415983220">穿中山装的不能惹</d>
<d p="215.48300170898,1,25,16777215,1496075477,0,7a3aa307,3416664572">牛顿都被艹了</d>
<d p="1293.8699951172,1,25,16777215,1496083200,0,dbdd59b4,3416899410">开始了，自爆吧，奥布</d>
<d p="1270.1500244141,1,25,16777215,1496108136,0,c0a14da3,3417256188">惊不惊喜，意不意外？</d>
<d p="415.90200805664,1,25,16777215,1496125276,0,96709a9f,3418098571">这飞镖还能飞回来？</d>
<d p="646.67602539062,1,25,16777215,1496125618,0,96709a9f,3418116056">膜法的2333333</d>
<d p="1191.4699707031,1,25,16777215,1496126072,0,1ca283d2,3418139284">这一任领导超级赞</d>
<d p="1360.3699951172,1,25,16777215,1496126247,0,1ca283d2,3418148339">ed换了</d>
<d p="1387.9499511719,1,25,16777215,1496126283,0,1ca283d2,3418150243">美炸</d>
<d p="34.419998168945,1,25,16777215,1496136413,0,511ab9e3,3418649638">居然有2个观众。。好激动~</d>
<d p="44.752998352051,1,25,16777215,1496136839,0,511ab9e3,3418669831">残存部队</d>
<d p="536.36401367188,1,25,16777215,1496136878,0,511ab9e3,3418671642">坚持！~~~</d>
<d p="543.06402587891,1,25,16777215,1496136909,0,511ab9e3,3418673098">这么省钱。。。的翻译=。 -</d>
<d p="611.32202148438,1,25,16777215,1496137035,0,511ab9e3,3418678968">精华 台词~~~~</d>
<d p="647.06500244141,1,25,16777215,1496137083,0,511ab9e3,3418681261">这叫声好傲娇=。 -</d>
<d p="676.19396972656,1,25,16777215,1496137225,0,511ab9e3,3418687746">有那么难打吗？~</d>
<d p="676.19396972656,1,25,16777215,1496137897,0,511ab9e3,3418720185">假到死，这么近一炮都没中</d>
<d p="30.167499542236,1,25,16777215,1496148879,0,a59e87ec,3419245090">来听晓之车</d>
<d p="1402.1800537109,1,25,16777215,1496155711,0,f4f15f1f,3419616994">中山装？？？</d>
<d p="1438.5300292969,1,25,16777215,1496155753,0,f4f15f1f,3419619322">强袭好帅</d>
<d p="1123.4599609375,1,25,16777215,1496167842,0,55118275,3420039819">神曲上线</d>
<d p="236.40299987793,1,25,16777215,1496222052,0,0faa80c7,3420973127">牛顿很多理论也是不完全正确的，包括万有引力</d>
<d p="321.62799072266,1,25,16777215,1496230342,0,bf6aa2b6,3421320905">阳电子破城炮对环境污染很大，大天使基本不再地球用。</d>
<d p="321.62799072266,1,25,16777215,1496230349,0,bf6aa2b6,3421321179">但是第二季的那谁就用的飞起。</d>
<d p="621.5009765625,1,25,16777215,1496230593,0,bf6aa2b6,3421331273">这明明是锁！</d>
<d p="654.59997558594,1,25,16777215,1496230629,0,bf6aa2b6,3421332708">-1s</d>
<d p="841.57000732422,1,25,16777215,1496234936,0,bf6aa2b6,3421499657">不传不传，这火传不起！</d>
<d p="971.02502441406,1,25,16777215,1496235101,0,bf6aa2b6,3421507541">对了，阿斯兰SD里面也绿了，真是，干脆染发算了</d>
<d p="1088.6999511719,1,25,16777215,1496235249,0,bf6aa2b6,3421514084">原版卡嘉莉开始哭的时候晓之车就到高潮了</d>
<d p="989.61401367188,1,25,16777215,1496241344,0,de9b5a2a,3421821719">狼在第二部才多妹子。。</d>
<d p="491.51800537109,1,25,16777215,1496245668,0,88284163,3422033375">擒贼先擒王啊！</d>
<d p="546.60498046875,1,25,16777215,1496286538,0,5e61a5c8,3422559308">暗中观察</d>
<d p="1294.5799560547,1,25,16777215,1496287284,0,5e61a5c8,3422574461">泪目</d>
<d p="1345.4699707031,1,25,16777215,1496312469,0,1f9a4966,3423263393">全体！向奥布之狮拔刀敬礼！</d>
<d p="653.58099365234,1,25,16777215,1496315739,0,ec4ffb9f,3423383822">这都能膜</d>
<d p="1365.4399414062,1,25,16777215,1496321931,0,2df7d8f4,3423635274">好美</d>
<d p="426.65701293945,1,25,16777215,1496331967,0,ef5e046c,3424106290">近战之王上线了</d>
<d p="228.60899353027,1,25,16711680,1496402608,0,7b2beb0c,3425633115">怎么不说是兵的厉害的，</d>
<d p="1181.9499511719,1,25,16777215,1496406637,0,2bc87f79,3425828025">是弟弟，妈的，神他妈哥哥</d>
<d p="493.74398803711,5,25,15138834,1496437278,0,98b7aab1,3426799750">我玩psp的sd敢达用大天使开场就先扫一炮阳电子破城炮哈哈</d>
<d p="1274.4899902344,1,25,16777215,1496463620,0,f3cf138c,3427324089">惊不惊喜，意不意外</d>
<d p="1435.4599609375,1,25,16777215,1496489106,0,7d22f2ea,3428342045">姐弟不可怕？我妹妹不可能这么可爱！！！！</d>
<d p="998.41302490234,1,25,16777215,1496495253,0,cfe87088,3428622169">来一起加入天人吧(⊙o⊙)</d>
<d p="870.91302490234,1,25,16777215,1496499183,0,5f09bc2a,3428821736">奥布耗不过对面</d>
<d p="942.84301757812,1,25,16777215,1496499783,0,b8f91163,3428853602">这应该是大天使号唯一一次在地球圈开阳电子炮</d>
<d p="204.07600402832,1,25,16777215,1496509656,0,b1d80b90,3429321107">话说你们竟然会让对方接近到近程导弹能打到的地方</d>
<d p="1005.2600097656,1,25,16777215,1496510526,0,b1d80b90,3429361662">话说你们不能趁他们不行去攻击战舰么=_=</d>
<d p="1322.9100341797,1,25,16777215,1496511352,0,d4f469cd,3429396267">莫名泪目</d>
<d p="902.88702392578,1,25,16777215,1496552816,0,4e3d3852,3430266440">女的可以繁衍后代，可以多生，一夫多妻可以增加人口</d>
<d p="350.70401000977,1,25,16777215,1496560127,0,74f83124,3430601945">爆种是需要某种情绪来刺激才能爆的</d>
<d p="1355.3000488281,1,25,16777215,1496561071,0,74f83124,3430640074">拉克丝就是美</d>
<d p="1349.75,1,25,16777215,1496574820,0,a6c47e14,3431213922">拂晓还在造</d>
<d p="1262.8599853516,1,25,15138834,1496582293,0,47f9fa4a,3431556484">深情对望23333</d>
<d p="1424.9000244141,1,25,16777215,1496587601,0,834e67ac,3431812569">阿斯兰的小眼神233333心疼</d>
<d p="778.61901855469,1,25,16777215,1496588872,0,c666de9f,3431877192">那居民怎么办？</d>
<d p="1373.9499511719,1,25,16777215,1496590972,0,56fbbcf2,3431975948">如果看了卡嘉丽的声优 可能是两种感觉…</d>
<d p="1380.5400390625,1,25,16777215,1496594532,0,664c171f,3432111032">这个拉丝提</d>
<d p="1404.2600097656,1,25,16777215,1496594571,0,664c171f,3432112184">海涅不是克隆。。</d>
<d p="1286.9399414062,1,25,16777215,1496640300,0,f95673dc,3432778927">因为字幕有人搞怪，破坏美感</d>
<d p="376.3030090332,1,25,16777215,1496640660,0,28c0e681,3432792259">ｍｓ终结者</d>
<d p="1119.5,5,25,16707842,1496652374,0,d4f26262,3433112290">晓之车上线</d>
<d p="13.371000289917,1,25,15138834,1496675008,0,5d8f7f6e,3434119875">晓之车，水之证，焰之绯我都挺喜欢的</d>
<d p="304.8330078125,1,25,16777215,1496742812,0,7ad99370,3435744683">23333</d>
<d p="805.93499755859,1,25,16777215,1496743389,0,7ad99370,3435768177">要自爆了要自爆了</d>
<d p="1050.4699707031,1,25,16777215,1496743659,0,7ad99370,3435779394">ti 是几声啊  </d>
<d p="1054.4300537109,1,25,16777215,1496743678,0,7ad99370,3435780220">ti 是几声啊</d>
<d p="737,1,25,16777215,1496744352,0,bf377e59,3435809119">不啊核能又不需要补给能量，只要补给实体弹吧。。。</d>
<d p="1134,1,25,16777215,1496744744,0,bf377e59,3435825002">感谢粉字字幕</d>
<d p="1261,1,25,16777215,1496744874,0,bf377e59,3435830546">自由的马力更强，但正义的速度更快</d>
<d p="362.16500854492,1,25,16777215,1496755491,0,4a80f1e6,3436355549">心悦VIP3上线</d>
<d p="864.80700683594,1,25,16777215,1496815040,0,9c0468d0,3437831097">实际上你看动画不了解奥布的战术有多糟糕</d>
<d p="1331.9000244141,1,25,16777215,1496824575,0,d66fcf5e,3438179252">献出心脏！</d>
<d p="376.81500244141,1,25,16777215,1496831556,0,47b7f849,3438484073">动不动就开打</d>
<d p="0.72000002861023,5,25,16707842,1496843442,0,bb32674d,3439086982">要上天了</d>
<d p="235.10499572754,1,25,16777215,1496859239,0,210674a1,3439712029">为什么之前那四架高达能灭一个舰队，这两个核动力的就不行？</d>
<d p="637.25799560547,1,25,16777215,1496894098,0,ee2c97f2,3440193319">如果不是裸睡为啥衣服这么整齐</d>
<d p="1151.0999755859,1,25,16777215,1496894504,0,ee2c97f2,3440206404">如果有00的拐弯炮就好玩了</d>
<d p="1313.7299804688,1,25,16777215,1496894677,0,ee2c97f2,3440212117">我只想知道他们怎么老是自爆</d>
<d p="1416.0300292969,1,25,16777215,1496898072,0,88ecc319,3440361028">食物链顶端的夫妇们</d>
<d p="143.66700744629,1,25,16777215,1496913841,0,992d50de,3440908922">＋1</d>
<d p="1350.9200439453,1,25,16777215,1496924719,0,9b601309,3441367497">莫名掉眼泪</d>
<d p="60.629001617432,5,25,16777215,1496930678,0,8ae3edf0,3441654760">听成了东京热……</d>
<d p="1315.3900146484,1,25,16777215,1496931432,0,dc218626,3441694553">QAQ</d>
<d p="1251.6500244141,1,25,14811775,1496937407,0,bb5e35b5,3441995189">正义的脸真的好看</d>
<d p="455.64801025391,1,25,16777215,1496987896,0,6ab6e056,3443039022">迪亚哥为了下面二两肉也是挺拼的</d>
<d p="60.604000091553,1,25,16777215,1497008962,0,5909e6af,3443819434">以上皆为逝世时间，为此鸣笛哀悼……</d>
<d p="532.26202392578,1,25,16777215,1497009495,0,5909e6af,3443846002">残存的不对，字幕组来给我解释解释，我读书少</d>
<d p="734.34698486328,1,25,15138834,1497009715,0,5909e6af,3443858151">爆种很耗体力好吧，用完基本没法继续打了</d>
<d p="871.42700195312,1,25,15138834,1497009891,0,5909e6af,3443866174">奥布缺少能实战的人才啊</d>
<d p="370.88400268555,1,25,16777215,1497010651,0,69b9440e,3443904291">卧槽，X6.</d>
<d p="148.73300170898,1,25,16777215,1497018546,0,04ee89fa,3444330683">晓之车上线</d>
<d p="1119.4200439453,1,25,16777215,1497061508,0,8a5ff14d,3445314915">还……还有这种操作</d>
<d p="931.791015625,5,25,41194,1497081971,0,1961dd0f,3446215374">其实这玩意往对面旗舰一扫就打完了</d>
<d p="729,1,25,16777215,1497087582,0,9dab688d,3446462721">核动力美滋滋</d>
<d p="956.84600830078,1,25,16777215,1497106011,0,d2556420,3447449944">大天使在种命还把阳电子炮改成温泉了</d>
<d p="1254.7399902344,1,25,16777215,1497119898,0,62fe10e0,3448105715">脚不是更长吗</d>
<d p="224.47900390625,1,25,16777215,1497156568,0,c4d9daf1,3449014327">人形机器人的机械效率要明显低下的多，但是我们愿意看啊</d>
<d p="344.7200012207,1,25,16777215,1497156639,0,c4d9daf1,3449018401">阿斯绿：基拉，你对拉克丝做了什么？基神：嘿嘿，爱</d>
<d p="621.40002441406,1,25,16777215,1497156945,0,c4d9daf1,3449035772"> 有seed不一定是新人类，新人类也不一定都有seed</d>
<d p="651.53997802734,1,25,16777215,1497156975,0,c4d9daf1,3449037478">蛤~~~~~</d>
<d p="856.08197021484,1,25,16777215,1497157179,0,c4d9daf1,3449049093">兴欣之火，可以燎原！</d>
<d p="947.27801513672,1,25,16777215,1497180695,0,6040d98d,3450195874">地球散热好吧？宇宙没有散热媒介</d>
<d p="998.71301269531,1,25,16777215,1497195304,0,572a7f09,3450969893">????</d>
<d p="2.8199999332428,1,25,16777215,1497243072,0,cf858cb1,3451849780">来听神曲</d>
<d p="1343.8900146484,1,25,15138834,1497271685,0,7de16cfa,3452948017">真男人……再也不见你胡子密了……</d>
<d p="1130.0300292969,1,25,16777215,1497354855,0,c7d158ae,3455221998">啊啊啊晓之车</d>
<d p="1317.8199462891,1,25,16777215,1497355065,0,c7d158ae,3455231676">一路走好QAQ</d>
<d p="734.42199707031,5,25,15138834,1497412793,0,e549147f,3456647168">能量多是因为是核能机，和主不主角没关系</d>
<d p="1393.4200439453,1,25,16777215,1497424001,0,89018552,3457050639">ed老是剧透啊</d>
<d p="227.60400390625,1,25,16777215,1497431712,0,2cc09883,3457270274">你们俩联手再都开爆种是无敌的</d>
<d p="758.11798095703,1,25,38979,1497432280,0,2cc09883,3457289051">基拉你的现任被别人</d>
<d p="944.65698242188,1,25,16777215,1497432515,0,2cc09883,3457296894">其实实在被逼急了可以乱发阳电子炮威胁他们</d>
<d p="947.10998535156,1,25,16777215,1497432392,0,2cc09883,3457297050">其实实在被逼急了可以乱发阳电子炮威胁他们</d>
<d p="952.63598632812,1,25,16777215,1497432509,0,2cc09883,3457297323">其实实在被逼急了可以乱发阳电子炮威胁他们</d>
<d p="232.84800720215,1,25,16777215,1497454159,0,5ca5e87a,3458311385">人形兵器是卖玩具，但用不起远程导弹是有设定的</d>
<d p="297.18899536133,1,25,16777215,1497454293,0,5ca5e87a,3458317877">迪亚哥他爹也是PLANT最高评议会议员</d>
<d p="870.10198974609,1,25,16777215,1497454657,0,5ca5e87a,3458334954">奥布就一个完全没有战略纵深的小国，不是鸡狼顶着撑不住一天</d>
<d p="1338.2800292969,1,25,16777215,1497465756,0,4b02400f,3458624958">主要毁灭质料</d>
<d p="1000.75,1,25,16777215,1497489662,0,648c9534,3458825187">你们懂个P，你们的妹子都是阿斯狼让出来的，他才是赢家</d>
<d p="105.00099945068,1,25,16777215,1497502899,0,a846d476,3459246647">2017615</d>
<d p="1281.4399414062,1,25,26367,1497503771,0,a846d476,3459283381">恭喜牵手成功</d>
<d p="161.55099487305,1,25,16777215,1497522171,0,e4403769,3459999100">一直觉得动漫里从嘴里放激光什么的基本都是反派</d>
<d p="1381.7800292969,1,25,16777215,1497543593,0,cbe269e8,3461036440">悲催的拉斯提</d>
<d p="949.32800292969,1,25,16777215,1497583710,0,0f716eb4,3461648393">奥布也有阳电子炮啊</d>
<d p="1320.0699462891,1,25,16777215,1497611620,0,cc46a17b,3462812743">流星一条</d>
<d p="1317.7399902344,1,25,16777215,1497611640,0,cc46a17b,3462813673">流星一条</d>
<d p="1300.2700195312,5,25,15138834,1497611674,0,cc46a17b,3462815238">流星一条</d>
<d p="653.07202148438,1,25,16777215,1497618845,0,5b16ac7a,3463199989">-1S</d>
<d p="1123.9499511719,5,25,16776960,1497619878,0,5b16ac7a,3463256968">风さそう木荫に俯せて泣いてる</d>
<d p="1132.6800537109,5,25,16776960,1497619902,0,5b16ac7a,3463258395">见も知らぬ私を私が见ていた</d>
<d p="1142.5699462891,5,25,16776960,1497619928,0,5b16ac7a,3463259887">逝く人の调べを奏でるギタ－ラ</d>
<d p="1153.5300292969,5,25,16776960,1497619949,0,5b16ac7a,3463261053">来ぬ人の叹きに星は落ちて</d>
<d p="1162.1899414062,5,25,16776960,1497619964,0,5b16ac7a,3463261939">行かないで、どんなに叫んでも</d>
<d p="1169.2299804688,5,25,16776960,1497619979,0,5b16ac7a,3463262736">オレンジの花びら静かに揺れるだけ</d>
<d p="1179.6099853516,5,25,16776960,1497619994,0,5b16ac7a,3463263680">やわらかな额に残された</d>
<d p="1187.4499511719,5,25,16776960,1497620009,0,5b16ac7a,3463264508">手のひらの记忆遥か</d>
<d p="1193.3499755859,5,25,16776960,1497620021,0,5b16ac7a,3463265207">とこしえのさよならつま弾く</d>
<d p="1215.8399658203,5,25,16776960,1497620050,0,5b16ac7a,3463266825">优しい手にすがる子供の心を</d>
<d p="1224.4599609375,5,25,16776960,1497620066,0,5b16ac7a,3463267751">燃えさかる车轮は振り払い进む</d>
<d p="1233.2099609375,5,25,16776960,1497620080,0,5b16ac7a,3463268565">逝く人の叹きを奏でてギタ－ラ</d>
<d p="1241.8900146484,5,25,16776960,1497620096,0,5b16ac7a,3463269447">胸の糸激しく掻き鸣らして</d>
<d p="1250.4799804688,5,25,16776960,1497620110,0,5b16ac7a,3463270309">哀しみに染まらない白さで</d>
<d p="1258.2700195312,5,25,16776960,1497620127,0,5b16ac7a,3463271234">オレンジの花びら揺れてた夏の影に</d>
<d p="1269.3000488281,5,25,16776960,1497620167,0,5b16ac7a,3463273517">やわらかな额を失くしても</d>
<d p="1276.7399902344,5,25,16776960,1497620182,0,5b16ac7a,3463274353">赤く染めた砂遥か越えて行く</d>
<d p="1284.4300537109,5,25,16776960,1497620229,0,5b16ac7a,3463277045">さよなら の リズム</d>
<d p="1299.3800048828,5,25,16776960,1497620249,0,5b16ac7a,3463278204">想い出を焼き尽くして进む大地に</d>
<d p="1307.5500488281,5,25,16776960,1497620262,0,5b16ac7a,3463278929">懐かしく芽吹いて行くものがあるの</d>
<d p="1169.6800537109,5,25,16776960,1497621426,0,5b16ac7a,3463345607">却只换来橙色花瓣的静静摇曳</d>
<d p="1180.5400390625,5,25,16776960,1497621440,0,5b16ac7a,3463346438">残留在柔嫩额头上的</d>
<d p="1187.9399414062,5,25,16776960,1497621455,0,5b16ac7a,3463347332">手掌中的遥远的记忆 </d>
<d p="1195.0300292969,5,25,16776960,1497621472,0,5b16ac7a,3463348299">只有永别的演奏  </d>
<d p="1217.25,5,25,16776960,1497621494,0,5b16ac7a,3463349538">以温柔的手支撑著孩子的心  </d>
<d p="1225.2299804688,5,25,16776960,1497621502,0,5b16ac7a,3463350027">拨开熊熊燃烧的车轮再前进</d>
<d p="1233.9599609375,5,25,16776960,1497621524,0,5b16ac7a,3463351382">吉他弹奏出逝人的叹息</d>
<d p="1285.4799804688,5,25,16776960,1497621607,0,5b16ac7a,3463356419">离别的旋律啊</d>
<d p="1299.8499755859,5,25,16776960,1497621621,0,5b16ac7a,3463357253">在回忆燃烧殆尽的大地上</d>
<d p="1308.4100341797,5,25,16776960,1497621630,0,5b16ac7a,3463357757">怀念的嫩芽正在生根发芽</d>
<d p="211.17999267578,1,25,16777215,1497625999,0,03738804,3463611903">快亲亲快亲亲快亲亲</d>
<d p="286.15899658203,1,25,16777215,1497627176,0,d74b45aa,3463677021">长的黑，没看见吧૧(●´৺`●)૭哈哈</d>
<d p="1249.4599609375,1,25,16777215,1497628174,0,d74b45aa,3463732276">哦！基佬！</d>
<d p="1316.0500488281,1,25,16777215,1497663263,0,47b3ef6a,3464372893">stella</d>
<d p="1428.8599853516,1,25,16777215,1497663398,0,47b3ef6a,3464376495">阿斯兰hhhhhhhh</d>
<d p="862.95697021484,1,25,16777215,1497710451,0,c4c91bab,3466727979">才发现玛硫他爸是第八舰队那个司令啊。。。</d>
<d p="1030.8000488281,1,25,16777215,1497712553,0,1802ccd7,3466860275">拂晓抗实弹很弱，ce71年开出来几个金恩就能灭掉。。。</d>
<d p="1041.8800048828,1,25,16777215,1497712638,0,1802ccd7,3466865529">拂晓抗实弹能力几乎没有，现在开出来几架金恩都能打掉</d>
<d p="9.8979997634888,1,25,16777215,1497755892,0,033361f6,3468023792">最喜欢这集</d>
<d p="14.237999916077,1,25,16777215,1497755885,0,033361f6,3468024317">最喜欢这集</d>
<d p="64.178001403809,1,25,16777215,1497755943,0,033361f6,3468027210">最喜欢的op</d>
<d p="82.27799987793,1,25,16777215,1497755982,0,033361f6,3468028462">170618</d>
<d p="748.85699462891,1,25,16777215,1497760323,0,1ef1f3df,3468254852">阿斯兰驾驶舱还是会打的</d>
<d p="872.91802978516,1,25,16777215,1497760390,0,1ef1f3df,3468258636">奥布很小的岛国，而且一直是中立，基本没有实战经验</d>
<d p="1196.4799804688,1,25,16777215,1497760565,0,1ef1f3df,3468268442">这个是草雉号吗？</d>
<d p="1354.4499511719,1,25,16777215,1497760743,0,1ef1f3df,3468278860">高达seed就服胡子密</d>
<d p="787.60400390625,1,25,16777215,1497768614,0,f6b7a4fb,3468716969">现在还没有命运这机</d>
<d p="1137.3000488281,1,25,16777215,1497774311,0,52c0fba4,3468999084">神曲上线</d>
<d p="1344.1300048828,1,25,16777215,1497871708,0,0a6adc5c,3472376698">向奥布之狮致敬</d>
<d p="1292.5799560547,1,25,16777215,1497880551,0,2814e542,3472875737">奥布这届领导层是真骨气</d>
<d p="1246.0799560547,1,25,16777215,1497925365,0,d952171d,3474000769">BO起喽！</d>
<d p="996.85699462891,1,25,16777215,1497957720,0,ebd4cb84,3475363016">伊撒古呢？？？</d>
<d p="379.9580078125,1,25,16777215,1497975868,0,fe8f8320,3476367143">自由在补兵啊</d>
<d p="901.94500732422,1,25,16777215,1498108424,0,f0a0d050,3480359387">因为缺人</d>
<d p="1261.7099609375,1,25,16777215,1498108724,0,2f006e24,3480373542">左手上的盾牌突然消失...</d>
<d p="746.875,1,25,16777215,1498124744,0,654d526d,3480998654">带个充电宝啊</d>
<d p="1317.8100585938,1,25,16777215,1498149838,0,8228183b,3482330935">哈哈哈，气不气啊</d>
<d p="762.74102783203,1,25,16777215,1498180671,0,08958e75,3482752180">强袭自由实在下一季开发出来的吧</d>
<d p="843.29302978516,1,25,16777215,1498196071,0,e78aff3f,3483377801">突然发现这就有四台机了</d>
<d p="1357.4599609375,1,25,16777215,1498196612,0,e78aff3f,3483404591">我还以为是弗雷</d>
<d p="1297.4499511719,1,25,16777215,1498222420,0,33aa5134,3484589889">不敢打中轨道加速装置，怎么能命中</d>
<d p="432.96899414062,1,25,16777215,1498222716,0,19758c40,3484611147">神意地球不如村雨太夸张了，至少也是核能机，出力都不是一个级别的</d>
<d p="1397.2299804688,1,25,16777215,1498223004,0,33aa5134,3484626953">哔了狗</d>
<d p="731.23699951172,1,25,16777215,1498229869,0,8aa0d9e0,3485028434">除此以外禁断还有反射光线的装置防御能力是三机中最强的</d>
<d p="1305.3199462891,1,25,16777215,1498273668,0,29ecec23,3486085639">自爆密码不会是2887吧？</d>
</i>